{
    "variables": [
        {
            "contractName": "OXDEAD",
            "varName": "_balances",
            "varType": "mapping(address => uint256)",
            "varBytes": 32,
            "varValue": {
                "0xcaf7a2d34e73861e5e138dc884d78a83d0ec5687": {
                    "contractName": null,
                    "varName": null,
                    "varType": "uint256",
                    "varBytes": 32,
                    "varValue": 386186538602837943909806615611966,
                    "varSlot": 64246399748908272600312374272536448286510207444337197194933313954023595773675,
                    "varOffset": 0
                },
                "0x000000000000000000000000000000000000dead": {
                    "contractName": null,
                    "varName": null,
                    "varType": "uint256",
                    "varBytes": 32,
                    "varValue": 500000000000000000000000000000000,
                    "varSlot": 31063888810065305784377451194046110542589701094491830545216746748656552103811,
                    "varOffset": 0
                },
                "0x416116c61b4dfa0f304c38379d4c773db99fc8c9": {
                    "contractName": null,
                    "varName": null,
                    "varType": "uint256",
                    "varBytes": 32,
                    "varValue": 13653756013,
                    "varSlot": 87891488489323019378276204612409952811464962607590697613067150107875189391780,
                    "varOffset": 0
                },
                "0xa10e3af40d3a4ebcb7406cbf3eb16c1a0acb1888": {
                    "contractName": null,
                    "varName": null,
                    "varType": "uint256",
                    "varBytes": 32,
                    "varValue": 6154548933911132511080657308295,
                    "varSlot": 31870606154496568945562369611796837757612375749288955286099093483583752528560,
                    "varOffset": 0
                },
                "0xf45b0aa0569612810fbf810c9230512c2cf312b1": {
                    "contractName": null,
                    "varName": null,
                    "varType": "uint256",
                    "varBytes": 32,
                    "varValue": 3020693109154712055353488620426,
                    "varSlot": 68697383736255736178305596797133563920641729226466984071760455509919083254884,
                    "varOffset": 0
                },
                "0xfa54a5603f1816ecaeb0c94c99bb24c8ecce5bad": {
                    "contractName": null,
                    "varName": null,
                    "varType": "uint256",
                    "varBytes": 32,
                    "varValue": 15475350701733530045583325557502,
                    "varSlot": 3307867980103969750695922480252595861595687276581546131614868207156080924370,
                    "varOffset": 0
                },
                "0xa3f3907d81f186860c199251330e0055453f0b9d": {
                    "contractName": null,
                    "varName": null,
                    "varType": "uint256",
                    "varBytes": 32,
                    "varValue": 14856272683658500883748636524912,
                    "varSlot": 68634349617495098048366751036354294820632662399212431676964269752818070277556,
                    "varOffset": 0
                },
                "0xba1f5254da44c86ddd7d1ec18b5c42a83cd3fca2": {
                    "contractName": null,
                    "varName": null,
                    "varType": "uint256",
                    "varBytes": 32,
                    "varValue": 14491226207055814674731685075580,
                    "varSlot": 11479824819040433356083282648901172723617378541116059778706945956902598878857,
                    "varOffset": 0
                },
                "0x007933790a4f00000099e9001629d9fe7775b800": {
                    "contractName": null,
                    "varName": null,
                    "varType": "uint256",
                    "varBytes": 32,
                    "varValue": 40000000000000,
                    "varSlot": 77940949937663614175228306040880741116478213162409033764568391629882741570988,
                    "varOffset": 0
                },
                "0x8899e36cb10b339f4823ec48bdf310909da9f99f": {
                    "contractName": null,
                    "varName": null,
                    "varType": "uint256",
                    "varBytes": 32,
                    "varValue": 1369382992607244,
                    "varSlot": 61126399997502100656757759510777526696990141256031518873230522631774584080637,
                    "varOffset": 0
                },
                "0xd795eb0248a093634b5b247f793512cef1d4caa6": {
                    "contractName": null,
                    "varName": null,
                    "varType": "uint256",
                    "varBytes": 32,
                    "varValue": 867974355786367590,
                    "varSlot": 63538075080933844885138316802134800254131737341461999816793237412656092508091,
                    "varOffset": 0
                },
                "0x32f3895ede4de3601c9e8fab0e88e8c4a7ba16ab": {
                    "contractName": null,
                    "varName": null,
                    "varType": "uint256",
                    "varBytes": 32,
                    "varValue": 271595788415622997629422173098,
                    "varSlot": 5058292255096637220859335616975104000827865716688329710505441757030877446151,
                    "varOffset": 0
                },
                "0x3da0cffa8a227f767336b31bc58f7d3e5791cdff": {
                    "contractName": null,
                    "varName": null,
                    "varType": "uint256",
                    "varBytes": 32,
                    "varValue": 448347142510102812596086645196,
                    "varSlot": 28243054738034666498216165350931646525274705055984198056281917435748178609851,
                    "varOffset": 0
                },
                "0x094b62692fe8a27161f51ac5686897a4a136ba6f": {
                    "contractName": null,
                    "varName": null,
                    "varType": "uint256",
                    "varBytes": 32,
                    "varValue": 0,
                    "varSlot": 89457971146376731433804659986389419098712885263652400655425782186396992087447,
                    "varOffset": 0
                },
                "0xa92cf4ac840e97b143ea5e787dfe3e6371cea096": {
                    "contractName": null,
                    "varName": null,
                    "varType": "uint256",
                    "varBytes": 32,
                    "varValue": 0,
                    "varSlot": 4798451267016199273499802118503300272239492557239712058611749199559492024785,
                    "varOffset": 0
                },
                "0x00000000a991c429ee2ec6df19d40fe0c80088b8": {
                    "contractName": null,
                    "varName": null,
                    "varType": "uint256",
                    "varBytes": 32,
                    "varValue": 2,
                    "varSlot": 519426537468644323674556318005997876401261280406569082560109975263175357743,
                    "varOffset": 0
                },
                "0xeba89a456d397c63f162e2ea43b510c003fdb68b": {
                    "contractName": null,
                    "varName": null,
                    "varType": "uint256",
                    "varBytes": 32,
                    "varValue": 165822980571809124,
                    "varSlot": 90656332876846459931954245600368513732379571424242521003837740038695106323823,
                    "varOffset": 0
                },
                "0x4c8d78a40c45af71c448f35c6ad153d0a7b9651f": {
                    "contractName": null,
                    "varName": null,
                    "varType": "uint256",
                    "varBytes": 32,
                    "varValue": 2815631868078873056187639166013,
                    "varSlot": 62368057718695644380556378122013948617280699260325192712261957756369342649579,
                    "varOffset": 0
                },
                "0xe5956b4807116084e595057de6d795b7fde12a3b": {
                    "contractName": null,
                    "varName": null,
                    "varType": "uint256",
                    "varBytes": 32,
                    "varValue": 6838734968983772541116206423070,
                    "varSlot": 14960951050031377799746456741894357506323604122002214534992964163629521782248,
                    "varOffset": 0
                },
                "0x9ebaecfa86895d7c17cb97813726814c32a049a5": {
                    "contractName": null,
                    "varName": null,
                    "varType": "uint256",
                    "varBytes": 32,
                    "varValue": 5221934096913513578755048009236,
                    "varSlot": 102706325597907857091917466994555737568090368582040702913820211689818342593677,
                    "varOffset": 0
                },
                "0xf27bca916c31d12fb63daa3f50334752001e4591": {
                    "contractName": null,
                    "varName": null,
                    "varType": "uint256",
                    "varBytes": 32,
                    "varValue": 2854831804350406010881086957025,
                    "varSlot": 102045117091276503852076732034710786982169107099505552122657337952025887664939,
                    "varOffset": 0
                },
                "0x62c63c9ef30f17ed2309db322ebce0b62ea1a988": {
                    "contractName": null,
                    "varName": null,
                    "varType": "uint256",
                    "varBytes": 32,
                    "varValue": 6932599512961330260102476392291,
                    "varSlot": 91647698044710020183292087897761563591040268931523176258952002756545049072033,
                    "varOffset": 0
                },
                "0xe8c060f8052e07423f71d445277c61ac5138a2e5": {
                    "contractName": null,
                    "varName": null,
                    "varType": "uint256",
                    "varBytes": 32,
                    "varValue": 1,
                    "varSlot": 114757285817610909414243277388706620399352517069212886112953142159629493733235,
                    "varOffset": 0
                },
                "0x874044bf92f750bb913d80d6f4daed427447d6ce": {
                    "contractName": null,
                    "varName": null,
                    "varType": "uint256",
                    "varBytes": 32,
                    "varValue": 4586055413920543197981512556889,
                    "varSlot": 27910461620350977762084181167248512512412762783681156710128971772279156105097,
                    "varOffset": 0
                },
                "0x413338195475a3564d3c8c732120cd11ce611b24": {
                    "contractName": null,
                    "varName": null,
                    "varType": "uint256",
                    "varBytes": 32,
                    "varValue": 2619259706335798183182313599100,
                    "varSlot": 50751411131389774946652188877945043812112409981965688982557873660071236161284,
                    "varOffset": 0
                },
                "0x8ca0cfcc787cf9d4f01f32f615ef7c65eab8049d": {
                    "contractName": null,
                    "varName": null,
                    "varType": "uint256",
                    "varBytes": 32,
                    "varValue": 1937070741385785644079054869052,
                    "varSlot": 65154584585609127385532181359254819215338521205775099493026251033954229232768,
                    "varOffset": 0
                },
                "0x3d909b6cb958a32f1a6e0d016c387a3a2c8decd1": {
                    "contractName": null,
                    "varName": null,
                    "varType": "uint256",
                    "varBytes": 32,
                    "varValue": 1278576895587437599619344699113,
                    "varSlot": 19979903284752058273361153813728013105642509476482964929277154931042824197841,
                    "varOffset": 0
                },
                "0x31000adcd6476b052cc1baa9c80c4af373bebbf9": {
                    "contractName": null,
                    "varName": null,
                    "varType": "uint256",
                    "varBytes": 32,
                    "varValue": 252046848860598,
                    "varSlot": 108878448286007028958256786104868671147985727899062922087081017884831065299108,
                    "varOffset": 0
                },
                "0x9ea8a4e4db393141d9c5bcfcf82114eb56128fcb": {
                    "contractName": null,
                    "varName": null,
                    "varType": "uint256",
                    "varBytes": 32,
                    "varValue": 6933382494430773031441314258604,
                    "varSlot": 93207273367751434598183209846787729385378036663931775434787140452605503785311,
                    "varOffset": 0
                },
                "0x7db1411ec334c5e4dcb9433d2e477e82a0229504": {
                    "contractName": null,
                    "varName": null,
                    "varType": "uint256",
                    "varBytes": 32,
                    "varValue": 17077349327773371547344232152060,
                    "varSlot": 79017812399318019944443223692157229257039508048962589001535034298017656660581,
                    "varOffset": 0
                }
            },
            "varSlot": 0,
            "varOffset": 0,
            "key_var_type": {
                "contractName": null,
                "varName": null,
                "varType": "address",
                "varBytes": 20,
                "varValue": null,
                "varSlot": null,
                "varOffset": null
            },
            "val_var_type": {
                "contractName": null,
                "varName": null,
                "varType": "uint256",
                "varBytes": 32,
                "varValue": null,
                "varSlot": null,
                "varOffset": null
            }
        },
        {
            "contractName": "OXDEAD",
            "varName": "_allowances",
            "varType": "mapping(address => mapping(address => uint256))",
            "varBytes": 32,
            "varValue": {
                "0xcaf7a2d34e73861e5e138dc884d78a83d0ec5687": {
                    "contractName": null,
                    "varName": null,
                    "varType": "mapping(address => uint256)",
                    "varBytes": 32,
                    "varValue": {
                        "0x7a250d5630b4cf539739df2c5dacb4c659f2488d": {
                            "contractName": null,
                            "varName": null,
                            "varType": "uint256",
                            "varBytes": 32,
                            "varValue": 115792089237316195423570985008687907853269984165640564039457584007913129639935,
                            "varSlot": 43720751869001022756576730335235906971394293080622339695730572948821818099347,
                            "varOffset": 0
                        }
                    },
                    "varSlot": 80216605790689910061638251404431102856017053503662652513679176104090491358896,
                    "varOffset": null,
                    "key_var_type": {
                        "contractName": null,
                        "varName": null,
                        "varType": "address",
                        "varBytes": 20,
                        "varValue": null,
                        "varSlot": null,
                        "varOffset": null
                    },
                    "val_var_type": {
                        "contractName": null,
                        "varName": null,
                        "varType": "uint256",
                        "varBytes": 32,
                        "varValue": null,
                        "varSlot": null,
                        "varOffset": null
                    }
                },
                "0xf45b0aa0569612810fbf810c9230512c2cf312b1": {
                    "contractName": null,
                    "varName": null,
                    "varType": "mapping(address => uint256)",
                    "varBytes": 32,
                    "varValue": {
                        "0x7a250d5630b4cf539739df2c5dacb4c659f2488d": {
                            "contractName": null,
                            "varName": null,
                            "varType": "uint256",
                            "varBytes": 32,
                            "varValue": 115792089237316195423570985008687907853269984665640564039457584007913129639935,
                            "varSlot": 35265783656005166467641421393131109000330723197994725949802299991242640970112,
                            "varOffset": 0
                        }
                    },
                    "varSlot": 33803710788364330007919312110387810404347491722436905558300921723535061108314,
                    "varOffset": null,
                    "key_var_type": {
                        "contractName": null,
                        "varName": null,
                        "varType": "address",
                        "varBytes": 20,
                        "varValue": null,
                        "varSlot": null,
                        "varOffset": null
                    },
                    "val_var_type": {
                        "contractName": null,
                        "varName": null,
                        "varType": "uint256",
                        "varBytes": 32,
                        "varValue": null,
                        "varSlot": null,
                        "varOffset": null
                    }
                },
                "0xa3f3907d81f186860c199251330e0055453f0b9d": {
                    "contractName": null,
                    "varName": null,
                    "varType": "mapping(address => uint256)",
                    "varBytes": 32,
                    "varValue": {
                        "0x7a250d5630b4cf539739df2c5dacb4c659f2488d": {
                            "contractName": null,
                            "varName": null,
                            "varType": "uint256",
                            "varBytes": 32,
                            "varValue": 115792089237316195423570985008687907853269984665640564039457584007913129639935,
                            "varSlot": 101038204434701036690978397794149948520775700892492965146861553957582213329352,
                            "varOffset": 0
                        }
                    },
                    "varSlot": 86950600958101321015322614744157121153164650210392731114390860496303243927673,
                    "varOffset": null,
                    "key_var_type": {
                        "contractName": null,
                        "varName": null,
                        "varType": "address",
                        "varBytes": 20,
                        "varValue": null,
                        "varSlot": null,
                        "varOffset": null
                    },
                    "val_var_type": {
                        "contractName": null,
                        "varName": null,
                        "varType": "uint256",
                        "varBytes": 32,
                        "varValue": null,
                        "varSlot": null,
                        "varOffset": null
                    }
                },
                "0xba1f5254da44c86ddd7d1ec18b5c42a83cd3fca2": {
                    "contractName": null,
                    "varName": null,
                    "varType": "mapping(address => uint256)",
                    "varBytes": 32,
                    "varValue": {
                        "0x7a250d5630b4cf539739df2c5dacb4c659f2488d": {
                            "contractName": null,
                            "varName": null,
                            "varType": "uint256",
                            "varBytes": 32,
                            "varValue": 115792089237316195423570985008687907853269984665640564039457584007913129639935,
                            "varSlot": 109001009307126882280946465161216455184509715503959960664592373792387037661622,
                            "varOffset": 0
                        }
                    },
                    "varSlot": 42947041342824414312815789232024927197093978808695043217844341730676368220648,
                    "varOffset": null,
                    "key_var_type": {
                        "contractName": null,
                        "varName": null,
                        "varType": "address",
                        "varBytes": 20,
                        "varValue": null,
                        "varSlot": null,
                        "varOffset": null
                    },
                    "val_var_type": {
                        "contractName": null,
                        "varName": null,
                        "varType": "uint256",
                        "varBytes": 32,
                        "varValue": null,
                        "varSlot": null,
                        "varOffset": null
                    }
                },
                "0xfa54a5603f1816ecaeb0c94c99bb24c8ecce5bad": {
                    "contractName": null,
                    "varName": null,
                    "varType": "mapping(address => uint256)",
                    "varBytes": 32,
                    "varValue": {
                        "0x7a250d5630b4cf539739df2c5dacb4c659f2488d": {
                            "contractName": null,
                            "varName": null,
                            "varType": "uint256",
                            "varBytes": 32,
                            "varValue": 115792089237316195423570985008687907853269984665640564039457584007913129639935,
                            "varSlot": 94693062462509977149155469859023801788993270878970282900111005589792740745892,
                            "varOffset": 0
                        }
                    },
                    "varSlot": 7072316162263950622621175346603387975963408158834872498186933549333558841247,
                    "varOffset": null,
                    "key_var_type": {
                        "contractName": null,
                        "varName": null,
                        "varType": "address",
                        "varBytes": 20,
                        "varValue": null,
                        "varSlot": null,
                        "varOffset": null
                    },
                    "val_var_type": {
                        "contractName": null,
                        "varName": null,
                        "varType": "uint256",
                        "varBytes": 32,
                        "varValue": null,
                        "varSlot": null,
                        "varOffset": null
                    }
                },
                "0xd795eb0248a093634b5b247f793512cef1d4caa6": {
                    "contractName": null,
                    "varName": null,
                    "varType": "mapping(address => uint256)",
                    "varBytes": 32,
                    "varValue": {
                        "0x7a250d5630b4cf539739df2c5dacb4c659f2488d": {
                            "contractName": null,
                            "varName": null,
                            "varType": "uint256",
                            "varBytes": 32,
                            "varValue": 115792089237316195423570985008687907853269984634152758959220584007913129639935,
                            "varSlot": 108769889455813717583497875345651669932069703414606544431696668897949651320043,
                            "varOffset": 0
                        }
                    },
                    "varSlot": 4516455905222521633492936775774405912849275448431941904823160188166750534864,
                    "varOffset": null,
                    "key_var_type": {
                        "contractName": null,
                        "varName": null,
                        "varType": "address",
                        "varBytes": 20,
                        "varValue": null,
                        "varSlot": null,
                        "varOffset": null
                    },
                    "val_var_type": {
                        "contractName": null,
                        "varName": null,
                        "varType": "uint256",
                        "varBytes": 32,
                        "varValue": null,
                        "varSlot": null,
                        "varOffset": null
                    }
                },
                "0x8899e36cb10b339f4823ec48bdf310909da9f99f": {
                    "contractName": null,
                    "varName": null,
                    "varType": "mapping(address => uint256)",
                    "varBytes": 32,
                    "varValue": {
                        "0x7a250d5630b4cf539739df2c5dacb4c659f2488d": {
                            "contractName": null,
                            "varName": null,
                            "varType": "uint256",
                            "varBytes": 32,
                            "varValue": 115792089237316195423570985008687907853269984635039509795594267007913129639936,
                            "varSlot": 68795516972934413963025272456434647361191484023115982499935997218604821774522,
                            "varOffset": 0
                        }
                    },
                    "varSlot": 93903888672342631042141753044261081224909986607505596922806879520432818276943,
                    "varOffset": null,
                    "key_var_type": {
                        "contractName": null,
                        "varName": null,
                        "varType": "address",
                        "varBytes": 20,
                        "varValue": null,
                        "varSlot": null,
                        "varOffset": null
                    },
                    "val_var_type": {
                        "contractName": null,
                        "varName": null,
                        "varType": "uint256",
                        "varBytes": 32,
                        "varValue": null,
                        "varSlot": null,
                        "varOffset": null
                    }
                },
                "0x32f3895ede4de3601c9e8fab0e88e8c4a7ba16ab": {
                    "contractName": null,
                    "varName": null,
                    "varType": "mapping(address => uint256)",
                    "varBytes": 32,
                    "varValue": {
                        "0x7a250d5630b4cf539739df2c5dacb4c659f2488d": {
                            "contractName": null,
                            "varName": null,
                            "varType": "uint256",
                            "varBytes": 32,
                            "varValue": 115792089237316195423570985008687907853269984665640564039457584007913129639935,
                            "varSlot": 83830916297781523431551042708445988544565218622405468572669874456429522684044,
                            "varOffset": 0
                        }
                    },
                    "varSlot": 91935579384873303015779349250003674178177741689146426075416888066656277466259,
                    "varOffset": null,
                    "key_var_type": {
                        "contractName": null,
                        "varName": null,
                        "varType": "address",
                        "varBytes": 20,
                        "varValue": null,
                        "varSlot": null,
                        "varOffset": null
                    },
                    "val_var_type": {
                        "contractName": null,
                        "varName": null,
                        "varType": "uint256",
                        "varBytes": 32,
                        "varValue": null,
                        "varSlot": null,
                        "varOffset": null
                    }
                },
                "0x094b62692fe8a27161f51ac5686897a4a136ba6f": {
                    "contractName": null,
                    "varName": null,
                    "varType": "mapping(address => uint256)",
                    "varBytes": 32,
                    "varValue": {
                        "0x7a250d5630b4cf539739df2c5dacb4c659f2488d": {
                            "contractName": null,
                            "varName": null,
                            "varType": "uint256",
                            "varBytes": 32,
                            "varValue": 115792089237316195423570985008687907853269984648350710181311867083319019044418,
                            "varSlot": 48627178043733132984247988740402599123175808680166712909426817107340655519899,
                            "varOffset": 0
                        }
                    },
                    "varSlot": 36094426465823966463155881115803174175695104392071359343146784000267769196834,
                    "varOffset": null,
                    "key_var_type": {
                        "contractName": null,
                        "varName": null,
                        "varType": "address",
                        "varBytes": 20,
                        "varValue": null,
                        "varSlot": null,
                        "varOffset": null
                    },
                    "val_var_type": {
                        "contractName": null,
                        "varName": null,
                        "varType": "uint256",
                        "varBytes": 32,
                        "varValue": null,
                        "varSlot": null,
                        "varOffset": null
                    }
                },
                "0x3da0cffa8a227f767336b31bc58f7d3e5791cdff": {
                    "contractName": null,
                    "varName": null,
                    "varType": "mapping(address => uint256)",
                    "varBytes": 32,
                    "varValue": {
                        "0x68b3465833fb72a70ecdf485e0e4c7bd8665fc45": {
                            "contractName": null,
                            "varName": null,
                            "varType": "uint256",
                            "varBytes": 32,
                            "varValue": 115792089237316195423570985008687907853269984665640564039457584007913129639935,
                            "varSlot": 49044424010786382746323289361754742881596881025038997805163002608083332658276,
                            "varOffset": 0
                        }
                    },
                    "varSlot": 8135262949473313563744692201867425565308358167437026836256208130579202596566,
                    "varOffset": null,
                    "key_var_type": {
                        "contractName": null,
                        "varName": null,
                        "varType": "address",
                        "varBytes": 20,
                        "varValue": null,
                        "varSlot": null,
                        "varOffset": null
                    },
                    "val_var_type": {
                        "contractName": null,
                        "varName": null,
                        "varType": "uint256",
                        "varBytes": 32,
                        "varValue": null,
                        "varSlot": null,
                        "varOffset": null
                    }
                },
                "0xeba89a456d397c63f162e2ea43b510c003fdb68b": {
                    "contractName": null,
                    "varName": null,
                    "varType": "mapping(address => uint256)",
                    "varBytes": 32,
                    "varValue": {
                        "0x7a250d5630b4cf539739df2c5dacb4c659f2488d": {
                            "contractName": null,
                            "varName": null,
                            "varType": "uint256",
                            "varBytes": 32,
                            "varValue": 115792089237316195423570985008687907853269984662422982950329584007913129639935,
                            "varSlot": 111019686753786311886766731931476640355704397897004887150506924462487184390724,
                            "varOffset": 0
                        }
                    },
                    "varSlot": 32300490849131546820975470391545590492983350517206109974664787161696104205614,
                    "varOffset": null,
                    "key_var_type": {
                        "contractName": null,
                        "varName": null,
                        "varType": "address",
                        "varBytes": 20,
                        "varValue": null,
                        "varSlot": null,
                        "varOffset": null
                    },
                    "val_var_type": {
                        "contractName": null,
                        "varName": null,
                        "varType": "uint256",
                        "varBytes": 32,
                        "varValue": null,
                        "varSlot": null,
                        "varOffset": null
                    }
                },
                "0xa92cf4ac840e97b143ea5e787dfe3e6371cea096": {
                    "contractName": null,
                    "varName": null,
                    "varType": "mapping(address => uint256)",
                    "varBytes": 32,
                    "varValue": {
                        "0x68b3465833fb72a70ecdf485e0e4c7bd8665fc45": {
                            "contractName": null,
                            "varName": null,
                            "varType": "uint256",
                            "varBytes": 32,
                            "varValue": 115792089237316195423570985008687907853269984642448759295981679913461724223994,
                            "varSlot": 107572032768948634013292385170684288891932885711737217343551133230190616353395,
                            "varOffset": 0
                        }
                    },
                    "varSlot": 81173315625671269328566493870441700375721465795853613465900767812988353456254,
                    "varOffset": null,
                    "key_var_type": {
                        "contractName": null,
                        "varName": null,
                        "varType": "address",
                        "varBytes": 20,
                        "varValue": null,
                        "varSlot": null,
                        "varOffset": null
                    },
                    "val_var_type": {
                        "contractName": null,
                        "varName": null,
                        "varType": "uint256",
                        "varBytes": 32,
                        "varValue": null,
                        "varSlot": null,
                        "varOffset": null
                    }
                },
                "0x9ebaecfa86895d7c17cb97813726814c32a049a5": {
                    "contractName": null,
                    "varName": null,
                    "varType": "mapping(address => uint256)",
                    "varBytes": 32,
                    "varValue": {
                        "0x25553828f22bdd19a20e4f12f052903cb474a335": {
                            "contractName": null,
                            "varName": null,
                            "varType": "uint256",
                            "varBytes": 32,
                            "varValue": 115792089237316195423570985008687907853269984665640564039457584007913129639935,
                            "varSlot": 58696667013831930407096022892071628546903179182419397848678182906725187144138,
                            "varOffset": 0
                        }
                    },
                    "varSlot": 44060863748877539343950165189994614661992245359878560444115363666115947794767,
                    "varOffset": null,
                    "key_var_type": {
                        "contractName": null,
                        "varName": null,
                        "varType": "address",
                        "varBytes": 20,
                        "varValue": null,
                        "varSlot": null,
                        "varOffset": null
                    },
                    "val_var_type": {
                        "contractName": null,
                        "varName": null,
                        "varType": "uint256",
                        "varBytes": 32,
                        "varValue": null,
                        "varSlot": null,
                        "varOffset": null
                    }
                },
                "0xe5956b4807116084e595057de6d795b7fde12a3b": {
                    "contractName": null,
                    "varName": null,
                    "varType": "mapping(address => uint256)",
                    "varBytes": 32,
                    "varValue": {
                        "0xcb859ea579b28e02b87a1fde08d087ab9dbe5149": {
                            "contractName": null,
                            "varName": null,
                            "varType": "uint256",
                            "varBytes": 32,
                            "varValue": 115792089237316195423570985008687907853269984665640564039457584007913129639935,
                            "varSlot": 50191865092344946895300047882424712946268168605631968867953264117382777875326,
                            "varOffset": 0
                        }
                    },
                    "varSlot": 23335098507332441025028217573203937703182644744698695923979500198156864436994,
                    "varOffset": null,
                    "key_var_type": {
                        "contractName": null,
                        "varName": null,
                        "varType": "address",
                        "varBytes": 20,
                        "varValue": null,
                        "varSlot": null,
                        "varOffset": null
                    },
                    "val_var_type": {
                        "contractName": null,
                        "varName": null,
                        "varType": "uint256",
                        "varBytes": 32,
                        "varValue": null,
                        "varSlot": null,
                        "varOffset": null
                    }
                },
                "0x62c63c9ef30f17ed2309db322ebce0b62ea1a988": {
                    "contractName": null,
                    "varName": null,
                    "varType": "mapping(address => uint256)",
                    "varBytes": 32,
                    "varValue": {
                        "0x7a250d5630b4cf539739df2c5dacb4c659f2488d": {
                            "contractName": null,
                            "varName": null,
                            "varType": "uint256",
                            "varBytes": 32,
                            "varValue": 115792089237316195423570985008687907853269984665640564039457584007913129639935,
                            "varSlot": 87790641205027096667713718935149059202949991264902309103110805923004124696638,
                            "varOffset": 0
                        }
                    },
                    "varSlot": 14191530519987966113151458504802754089191862779453592647562068749333040525848,
                    "varOffset": null,
                    "key_var_type": {
                        "contractName": null,
                        "varName": null,
                        "varType": "address",
                        "varBytes": 20,
                        "varValue": null,
                        "varSlot": null,
                        "varOffset": null
                    },
                    "val_var_type": {
                        "contractName": null,
                        "varName": null,
                        "varType": "uint256",
                        "varBytes": 32,
                        "varValue": null,
                        "varSlot": null,
                        "varOffset": null
                    }
                },
                "0x8ca0cfcc787cf9d4f01f32f615ef7c65eab8049d": {
                    "contractName": null,
                    "varName": null,
                    "varType": "mapping(address => uint256)",
                    "varBytes": 32,
                    "varValue": {
                        "0x7a250d5630b4cf539739df2c5dacb4c659f2488d": {
                            "contractName": null,
                            "varName": null,
                            "varType": "uint256",
                            "varBytes": 32,
                            "varValue": 115792089237316195423570985008687907853269984665640564039457584007913129639935,
                            "varSlot": 18369891346657128416023937255627558931828904018934254643484388942139559220322,
                            "varOffset": 0
                        }
                    },
                    "varSlot": 41967789885133042755632263582118567233021268773174363248782846327941951443559,
                    "varOffset": null,
                    "key_var_type": {
                        "contractName": null,
                        "varName": null,
                        "varType": "address",
                        "varBytes": 20,
                        "varValue": null,
                        "varSlot": null,
                        "varOffset": null
                    },
                    "val_var_type": {
                        "contractName": null,
                        "varName": null,
                        "varType": "uint256",
                        "varBytes": 32,
                        "varValue": null,
                        "varSlot": null,
                        "varOffset": null
                    }
                },
                "0x31000adcd6476b052cc1baa9c80c4af373bebbf9": {
                    "contractName": null,
                    "varName": null,
                    "varType": "mapping(address => uint256)",
                    "varBytes": 32,
                    "varValue": {
                        "0x7a250d5630b4cf539739df2c5dacb4c659f2488d": {
                            "contractName": null,
                            "varName": null,
                            "varType": "uint256",
                            "varBytes": 32,
                            "varValue": 115792089237316195423570985008687907853269984660020383723894661007913129639936,
                            "varSlot": 86960139629509606279962969722554306327533788219566428282016996810145299729166,
                            "varOffset": 0
                        }
                    },
                    "varSlot": 31168562191446803557518511021908894044990479895136493920563142382149833294692,
                    "varOffset": null,
                    "key_var_type": {
                        "contractName": null,
                        "varName": null,
                        "varType": "address",
                        "varBytes": 20,
                        "varValue": null,
                        "varSlot": null,
                        "varOffset": null
                    },
                    "val_var_type": {
                        "contractName": null,
                        "varName": null,
                        "varType": "uint256",
                        "varBytes": 32,
                        "varValue": null,
                        "varSlot": null,
                        "varOffset": null
                    }
                },
                "0x9ea8a4e4db393141d9c5bcfcf82114eb56128fcb": {
                    "contractName": null,
                    "varName": null,
                    "varType": "mapping(address => uint256)",
                    "varBytes": 32,
                    "varValue": {
                        "0x7a250d5630b4cf539739df2c5dacb4c659f2488d": {
                            "contractName": null,
                            "varName": null,
                            "varType": "uint256",
                            "varBytes": 32,
                            "varValue": 115792089237316195423570985008687907853269984665640564039457584007913129639935,
                            "varSlot": 81778609931199957964328764443762468647445180820351186080035451417021968854095,
                            "varOffset": 0
                        }
                    },
                    "varSlot": 76844909821728951016274403698204082827049153531007912510775495814828314098300,
                    "varOffset": null,
                    "key_var_type": {
                        "contractName": null,
                        "varName": null,
                        "varType": "address",
                        "varBytes": 20,
                        "varValue": null,
                        "varSlot": null,
                        "varOffset": null
                    },
                    "val_var_type": {
                        "contractName": null,
                        "varName": null,
                        "varType": "uint256",
                        "varBytes": 32,
                        "varValue": null,
                        "varSlot": null,
                        "varOffset": null
                    }
                },
                "0x4c8d78a40c45af71c448f35c6ad153d0a7b9651f": {
                    "contractName": null,
                    "varName": null,
                    "varType": "mapping(address => uint256)",
                    "varBytes": 32,
                    "varValue": {
                        "0x7a250d5630b4cf539739df2c5dacb4c659f2488d": {
                            "contractName": null,
                            "varName": null,
                            "varType": "uint256",
                            "varBytes": 32,
                            "varValue": 115792089237316195423570985008687907853269984665640564039457584007913129639935,
                            "varSlot": 103414914257478792536520035116947042621692240614200243321236062293945151984939,
                            "varOffset": 0
                        }
                    },
                    "varSlot": 43436154773020733485527135600268780183827544878430382109827929300468608959129,
                    "varOffset": null,
                    "key_var_type": {
                        "contractName": null,
                        "varName": null,
                        "varType": "address",
                        "varBytes": 20,
                        "varValue": null,
                        "varSlot": null,
                        "varOffset": null
                    },
                    "val_var_type": {
                        "contractName": null,
                        "varName": null,
                        "varType": "uint256",
                        "varBytes": 32,
                        "varValue": null,
                        "varSlot": null,
                        "varOffset": null
                    }
                }
            },
            "varSlot": 1,
            "varOffset": 0,
            "key_var_type": {
                "contractName": null,
                "varName": null,
                "varType": "address",
                "varBytes": 20,
                "varValue": null,
                "varSlot": null,
                "varOffset": null
            },
            "val_var_type": {
                "contractName": null,
                "varName": null,
                "varType": "mapping(address => uint256)",
                "varBytes": 32,
                "varValue": null,
                "varSlot": null,
                "varOffset": null,
                "key_var_type": {
                    "contractName": null,
                    "varName": null,
                    "varType": "address",
                    "varBytes": 20,
                    "varValue": null,
                    "varSlot": null,
                    "varOffset": null
                },
                "val_var_type": {
                    "contractName": null,
                    "varName": null,
                    "varType": "uint256",
                    "varBytes": 32,
                    "varValue": null,
                    "varSlot": null,
                    "varOffset": null
                }
            }
        },
        {
            "contractName": "OXDEAD",
            "varName": "_totalSupply",
            "varType": "uint256",
            "varBytes": 32,
            "varValue": 1000000000000000000000000000000000,
            "varSlot": 2,
            "varOffset": 0
        },
        {
            "contractName": "OXDEAD",
            "varName": "_name",
            "varType": "string",
            "varBytes": 32,
            "varValue": "0x00000000000000000000000000000000000dEaD",
            "varSlot": 3,
            "varOffset": 0,
            "byteSize": 42,
            "toReadSlot": 87903029871075914254377627908054574944891091886930582284385770809450030037085
        },
        {
            "contractName": "OXDEAD",
            "varName": "_symbol",
            "varType": "string",
            "varBytes": 32,
            "varValue": "  0xdead",
            "varSlot": 4,
            "varOffset": 0,
            "byteSize": 8,
            "toReadSlot": 4
        },
        {
            "contractName": "OXDEAD",
            "varName": "_decimals",
            "varType": "uint8",
            "varBytes": 1,
            "varValue": 18,
            "varSlot": 5,
            "varOffset": 0
        }
    ]
}