{
    "variables": [
        {
            "contractName": "SocialMoney",
            "varName": "_balances",
            "varType": "mapping(address => uint256)",
            "varBytes": 32,
            "varValue": {
                "0x3f3a292b566d4932a7847f9e10d4d652667edaac": {
                    "contractName": null,
                    "varName": null,
                    "varType": "uint256",
                    "varBytes": 32,
                    "varValue": 10130881283,
                    "varSlot": 1688992958271480478329472583060175932795761895082965218744481674330109662986,
                    "varOffset": 0
                },
                "0xa32ff8ca08036337fabf50fa029812361cd176c8": {
                    "contractName": null,
                    "varName": null,
                    "varType": "uint256",
                    "varBytes": 32,
                    "varValue": 41375184174,
                    "varSlot": 48391369841528826026655419492599825825447039768504264917500699387281331751230,
                    "varOffset": 0
                },
                "0xbdeb21edd14f2b8438b0b9f01196e7c23fde1b73": {
                    "contractName": null,
                    "varName": null,
                    "varType": "uint256",
                    "varBytes": 32,
                    "varValue": 28072340765,
                    "varSlot": 87410523681755872266133791956418251526299174841841711554617786384709489818021,
                    "varOffset": 0
                },
                "0x6060b77a5d8309eb36374198e197072205ea2bb3": {
                    "contractName": null,
                    "varName": null,
                    "varType": "uint256",
                    "varBytes": 32,
                    "varValue": 0,
                    "varSlot": 28896386019106709546432012343558613269193420016871825265556865850346842939992,
                    "varOffset": 0
                },
                "0xbe30819e584c0ed313bcce7ae62f1e953952a941": {
                    "contractName": null,
                    "varName": null,
                    "varType": "uint256",
                    "varBytes": 32,
                    "varValue": 238719400,
                    "varSlot": 80391324364029097005853232204294223039810992124314053323970119172935882787818,
                    "varOffset": 0
                },
                "0xc78a95019c52ad9856aa764d6908e88d5b7930ee": {
                    "contractName": null,
                    "varName": null,
                    "varType": "uint256",
                    "varBytes": 32,
                    "varValue": 483100,
                    "varSlot": 36485521812874611456493747197836065578757083524819958812818451243240190313895,
                    "varOffset": 0
                },
                "0xa43ee0ddac31bf684c2d0a678964402322ad7210": {
                    "contractName": null,
                    "varName": null,
                    "varType": "uint256",
                    "varBytes": 32,
                    "varValue": 6072836,
                    "varSlot": 3328741690124565279976046607541546086584780131441723789386056858251731644094,
                    "varOffset": 0
                },
                "0x9ae8912ea6562957043c8d048641aa9b450c397f": {
                    "contractName": null,
                    "varName": null,
                    "varType": "uint256",
                    "varBytes": 32,
                    "varValue": 594200000,
                    "varSlot": 8674155411395304210179877405816706300995436653919471989746285782939072958124,
                    "varOffset": 0
                },
                "0x3293033bf7fc0ae9c73bbda3f3b225ac918945af": {
                    "contractName": null,
                    "varName": null,
                    "varType": "uint256",
                    "varBytes": 32,
                    "varValue": 691166310,
                    "varSlot": 72580492670513814789418281818445640409942235957029392561398569805375033650680,
                    "varOffset": 0
                },
                "0x9293c35d6e1524609b7221a1c9a8d52dc81ba62c": {
                    "contractName": null,
                    "varName": null,
                    "varType": "uint256",
                    "varBytes": 32,
                    "varValue": 150000000,
                    "varSlot": 32641241819034259924432387215266201622281103133946265775969596461464685128123,
                    "varOffset": 0
                },
                "0x046b390fa81167dc741d34b6dfd68714c88c3537": {
                    "contractName": null,
                    "varName": null,
                    "varType": "uint256",
                    "varBytes": 32,
                    "varValue": 1267754,
                    "varSlot": 96594184945489704851278693179044495125494713999102198129462270653946015262303,
                    "varOffset": 0
                },
                "0x73084e4338a64d73180d039fae40a0e92b105f35": {
                    "contractName": null,
                    "varName": null,
                    "varType": "uint256",
                    "varBytes": 32,
                    "varValue": 0,
                    "varSlot": 84724079207862022147225313766747404679538284899040356346846325415442523494606,
                    "varOffset": 0
                },
                "0xf0b4a1e6ac25d60af5e1f15a651c3d43b7064309": {
                    "contractName": null,
                    "varName": null,
                    "varType": "uint256",
                    "varBytes": 32,
                    "varValue": 100000000,
                    "varSlot": 97742686764244184549796288744488540959046935736307293166389322014305842258282,
                    "varOffset": 0
                },
                "0xed7ea8fd0b0c03dc91789776ec06f7b9a69075d1": {
                    "contractName": null,
                    "varName": null,
                    "varType": "uint256",
                    "varBytes": 32,
                    "varValue": 690000,
                    "varSlot": 93912641362860598398261115462949492564067038945207094850552029408577819907739,
                    "varOffset": 0
                },
                "0x583d2a5621366bd20877908357dc0924deb1da91": {
                    "contractName": null,
                    "varName": null,
                    "varType": "uint256",
                    "varBytes": 32,
                    "varValue": 1689800,
                    "varSlot": 42274045065294150600374228178672658953443947224608175571448113021740717470851,
                    "varOffset": 0
                },
                "0x05d806435c6dc9b13c05784ac5fa3425d4ff867e": {
                    "contractName": null,
                    "varName": null,
                    "varType": "uint256",
                    "varBytes": 32,
                    "varValue": 689800,
                    "varSlot": 50441290066025803260073774609820415097069722691346939572284026743562400889398,
                    "varOffset": 0
                },
                "0xa96a0545fb49a64d3fcd24945dfda401ad2dc05c": {
                    "contractName": null,
                    "varName": null,
                    "varType": "uint256",
                    "varBytes": 32,
                    "varValue": 302800,
                    "varSlot": 38837119211030545203284740479238230386812439884947591970597441324849915491798,
                    "varOffset": 0
                },
                "0x1530fc137f35b1b02299127696ed48bd1097b98d": {
                    "contractName": null,
                    "varName": null,
                    "varType": "uint256",
                    "varBytes": 32,
                    "varValue": 689800,
                    "varSlot": 47012979644387867745009720654793642152249180818151002191610626362094001130100,
                    "varOffset": 0
                },
                "0x21d08babae99a6038814d5fc38df7ace2341dc63": {
                    "contractName": null,
                    "varName": null,
                    "varType": "uint256",
                    "varBytes": 32,
                    "varValue": 689800,
                    "varSlot": 50731904126544637870453798415759017945783812608061170432265931198754403139431,
                    "varOffset": 0
                },
                "0xc0f030eac8b588817f8da16b9a2cdccc6451b25c": {
                    "contractName": null,
                    "varName": null,
                    "varType": "uint256",
                    "varBytes": 32,
                    "varValue": 689800,
                    "varSlot": 31838384059653425225921457891661475610013596917333015541393320485549903159655,
                    "varOffset": 0
                },
                "0x9e962e231a3a5b1960be8a40ec4dad71c082cc75": {
                    "contractName": null,
                    "varName": null,
                    "varType": "uint256",
                    "varBytes": 32,
                    "varValue": 689800,
                    "varSlot": 68079025918536685860632292101506573761303279796316231112445605401291737463327,
                    "varOffset": 0
                },
                "0xe4c81b6bc77f8fbd3c45a9722bb01f26334facab": {
                    "contractName": null,
                    "varName": null,
                    "varType": "uint256",
                    "varBytes": 32,
                    "varValue": 689800,
                    "varSlot": 97677833153692397616150914590193669046925001759400281039557718789086262066418,
                    "varOffset": 0
                },
                "0x36cf392542682afd63daae066ece38a40c6f2c59": {
                    "contractName": null,
                    "varName": null,
                    "varType": "uint256",
                    "varBytes": 32,
                    "varValue": 999800,
                    "varSlot": 22818095307092267251135835224178062482790125978558641210789863981504119175607,
                    "varOffset": 0
                },
                "0xf47ec7c789b52a82f5ca312244ddafd1a91ee55c": {
                    "contractName": null,
                    "varName": null,
                    "varType": "uint256",
                    "varBytes": 32,
                    "varValue": 889800,
                    "varSlot": 72777434402739306328432438354790799266926156760077319587373098174262985669338,
                    "varOffset": 0
                },
                "0x86babeb53683382890890147b714040d3ffb0ee7": {
                    "contractName": null,
                    "varName": null,
                    "varType": "uint256",
                    "varBytes": 32,
                    "varValue": 18621593778,
                    "varSlot": 93714733984684988692751579409143884133395125282014141486226137877752201271558,
                    "varOffset": 0
                },
                "0xfcfa4369eaa965ac4e36f1dd9fd2852c6542b0f7": {
                    "contractName": null,
                    "varName": null,
                    "varType": "uint256",
                    "varBytes": 32,
                    "varValue": 689800,
                    "varSlot": 37363431082187701990368633447210948116610422647057789716661731891790379618825,
                    "varOffset": 0
                },
                "0x7aa7421a2d2edbee0257901c46127dadf819bee4": {
                    "contractName": null,
                    "varName": null,
                    "varType": "uint256",
                    "varBytes": 32,
                    "varValue": 689800,
                    "varSlot": 89477668710694736501765146356997852541850474442147583366590267220010730573946,
                    "varOffset": 0
                },
                "0x3d86a399d159a248694a324783c41f3433451a61": {
                    "contractName": null,
                    "varName": null,
                    "varType": "uint256",
                    "varBytes": 32,
                    "varValue": 8000000,
                    "varSlot": 90609818456057524586945971378798119837138854205539170365880310267733156957887,
                    "varOffset": 0
                }
            },
            "varSlot": 0,
            "varOffset": 0,
            "key_var_type": {
                "contractName": null,
                "varName": null,
                "varType": "address",
                "varBytes": 20,
                "varValue": null,
                "varSlot": null,
                "varOffset": null
            },
            "val_var_type": {
                "contractName": null,
                "varName": null,
                "varType": "uint256",
                "varBytes": 32,
                "varValue": null,
                "varSlot": null,
                "varOffset": null
            }
        },
        {
            "contractName": "SocialMoney",
            "varName": "_allowed",
            "varType": "mapping(address => mapping(address => uint256))",
            "varBytes": 32,
            "varValue": {
                "0xc78a95019c52ad9856aa764d6908e88d5b7930ee": {
                    "contractName": null,
                    "varName": null,
                    "varType": "mapping(address => uint256)",
                    "varBytes": 32,
                    "varValue": {
                        "0x95e6f48254609a6ee006f7d493c8e5fb97094cef": {
                            "contractName": null,
                            "varName": null,
                            "varType": "uint256",
                            "varBytes": 32,
                            "varValue": 115792089237316195423570985008687907853269984665640564039457584007913125433035,
                            "varSlot": 5177469707109388869049632872374877983358344308325933320176958129378868986576,
                            "varOffset": 0
                        }
                    },
                    "varSlot": 82689758749655139271360540620525499088263487422025255382956998364763336798133,
                    "varOffset": null,
                    "key_var_type": {
                        "contractName": null,
                        "varName": null,
                        "varType": "address",
                        "varBytes": 20,
                        "varValue": null,
                        "varSlot": null,
                        "varOffset": null
                    },
                    "val_var_type": {
                        "contractName": null,
                        "varName": null,
                        "varType": "uint256",
                        "varBytes": 32,
                        "varValue": null,
                        "varSlot": null,
                        "varOffset": null
                    }
                },
                "0x9ae8912ea6562957043c8d048641aa9b450c397f": {
                    "contractName": null,
                    "varName": null,
                    "varType": "mapping(address => uint256)",
                    "varBytes": 32,
                    "varValue": {
                        "0xc36442b4a4522e871399cd717abdd847ab11fe88": {
                            "contractName": null,
                            "varName": null,
                            "varType": "uint256",
                            "varBytes": 32,
                            "varValue": 115792089237316195423570985008687907853269984665640564039457584007912435339935,
                            "varSlot": 42137305177523447419959857292348672216791218379360552953920249651936480023407,
                            "varOffset": 0
                        }
                    },
                    "varSlot": 58694167602643820121930118170678763685756914975375353583573341788984435771181,
                    "varOffset": null,
                    "key_var_type": {
                        "contractName": null,
                        "varName": null,
                        "varType": "address",
                        "varBytes": 20,
                        "varValue": null,
                        "varSlot": null,
                        "varOffset": null
                    },
                    "val_var_type": {
                        "contractName": null,
                        "varName": null,
                        "varType": "uint256",
                        "varBytes": 32,
                        "varValue": null,
                        "varSlot": null,
                        "varOffset": null
                    }
                },
                "0x046b390fa81167dc741d34b6dfd68714c88c3537": {
                    "contractName": null,
                    "varName": null,
                    "varType": "mapping(address => uint256)",
                    "varBytes": 32,
                    "varValue": {
                        "0xe592427a0aece92de3edee1f18e0157c05861564": {
                            "contractName": null,
                            "varName": null,
                            "varType": "uint256",
                            "varBytes": 32,
                            "varValue": 115792089237316195423570985008687907853269984665640564039457584007913129639935,
                            "varSlot": 100040732281952538184604973490133262106953179380251774162399476853175118676485,
                            "varOffset": 0
                        }
                    },
                    "varSlot": 25148780485356150486369057023034385134047809503566754433040124706511709473465,
                    "varOffset": null,
                    "key_var_type": {
                        "contractName": null,
                        "varName": null,
                        "varType": "address",
                        "varBytes": 20,
                        "varValue": null,
                        "varSlot": null,
                        "varOffset": null
                    },
                    "val_var_type": {
                        "contractName": null,
                        "varName": null,
                        "varType": "uint256",
                        "varBytes": 32,
                        "varValue": null,
                        "varSlot": null,
                        "varOffset": null
                    }
                },
                "0x73084e4338a64d73180d039fae40a0e92b105f35": {
                    "contractName": null,
                    "varName": null,
                    "varType": "mapping(address => uint256)",
                    "varBytes": 32,
                    "varValue": {
                        "0xe592427a0aece92de3edee1f18e0157c05861564": {
                            "contractName": null,
                            "varName": null,
                            "varType": "uint256",
                            "varBytes": 32,
                            "varValue": 115792089237316195423570985008687907853269984665640564039457584007913124639935,
                            "varSlot": 7203720470975795797082500685598986109692731448038682289044786597656892233095,
                            "varOffset": 0
                        }
                    },
                    "varSlot": 12444910976115463481462863379389493654088645199350968169829324427040203582663,
                    "varOffset": null,
                    "key_var_type": {
                        "contractName": null,
                        "varName": null,
                        "varType": "address",
                        "varBytes": 20,
                        "varValue": null,
                        "varSlot": null,
                        "varOffset": null
                    },
                    "val_var_type": {
                        "contractName": null,
                        "varName": null,
                        "varType": "uint256",
                        "varBytes": 32,
                        "varValue": null,
                        "varSlot": null,
                        "varOffset": null
                    }
                }
            },
            "varSlot": 1,
            "varOffset": 0,
            "key_var_type": {
                "contractName": null,
                "varName": null,
                "varType": "address",
                "varBytes": 20,
                "varValue": null,
                "varSlot": null,
                "varOffset": null
            },
            "val_var_type": {
                "contractName": null,
                "varName": null,
                "varType": "mapping(address => uint256)",
                "varBytes": 32,
                "varValue": null,
                "varSlot": null,
                "varOffset": null,
                "key_var_type": {
                    "contractName": null,
                    "varName": null,
                    "varType": "address",
                    "varBytes": 20,
                    "varValue": null,
                    "varSlot": null,
                    "varOffset": null
                },
                "val_var_type": {
                    "contractName": null,
                    "varName": null,
                    "varType": "uint256",
                    "varBytes": 32,
                    "varValue": null,
                    "varSlot": null,
                    "varOffset": null
                }
            }
        },
        {
            "contractName": "SocialMoney",
            "varName": "_totalSupply",
            "varType": "uint256",
            "varBytes": 32,
            "varValue": 100000000000,
            "varSlot": 2,
            "varOffset": 0
        },
        {
            "contractName": "SocialMoney",
            "varName": "name",
            "varType": "string",
            "varBytes": 32,
            "varValue": "snax",
            "varSlot": 3,
            "varOffset": 0,
            "byteSize": 4,
            "toReadSlot": 3
        },
        {
            "contractName": "SocialMoney",
            "varName": "symbol",
            "varType": "string",
            "varBytes": 32,
            "varValue": "SNAX",
            "varSlot": 4,
            "varOffset": 0,
            "byteSize": 4,
            "toReadSlot": 4
        },
        {
            "contractName": "SocialMoney",
            "varName": "decimals",
            "varType": "uint8",
            "varBytes": 1,
            "varValue": 4,
            "varSlot": 5,
            "varOffset": 0
        }
    ]
}