[
    {
        "func": "approve(spender,value)",
        "type": "PptType.EXIT",
        "executionType": "TxType.NORMAL",
        "preconditions": [],
        "postconditions": [],
        "falsified_preconditions": [],
        "falsified_postconditions": []
    },
    {
        "func": "approve(spender,value)",
        "type": "PptType.EXIT",
        "executionType": "TxType.REVERSION",
        "preconditions": [],
        "postconditions": [],
        "falsified_preconditions": [],
        "falsified_postconditions": []
    },
    {
        "func": "collectFrom(addresses,amounts,recipient)",
        "type": "PptType.EXIT",
        "executionType": "TxType.NORMAL",
        "preconditions": [],
        "postconditions": [],
        "falsified_preconditions": [],
        "falsified_postconditions": []
    },
    {
        "func": "collectFrom(addresses,amounts,recipient)",
        "type": "PptType.EXIT",
        "executionType": "TxType.REVERSION",
        "preconditions": [],
        "postconditions": [],
        "falsified_preconditions": [],
        "falsified_postconditions": []
    },
    {
        "func": "transferFrom(sender,recipient,amount)",
        "type": "PptType.EXIT",
        "executionType": "TxType.NORMAL",
        "preconditions": [],
        "postconditions": [],
        "falsified_preconditions": [],
        "falsified_postconditions": []
    },
    {
        "func": "transferFrom(sender,recipient,amount)",
        "type": "PptType.EXIT",
        "executionType": "TxType.REVERSION",
        "preconditions": [],
        "postconditions": [],
        "falsified_preconditions": [],
        "falsified_postconditions": []
    },
    {
        "func": "increaseAllowance(spender,addedValue)",
        "type": "PptType.EXIT",
        "executionType": "TxType.NORMAL",
        "preconditions": [],
        "postconditions": [],
        "falsified_preconditions": [],
        "falsified_postconditions": []
    },
    {
        "func": "increaseAllowance(spender,addedValue)",
        "type": "PptType.EXIT",
        "executionType": "TxType.REVERSION",
        "preconditions": [],
        "postconditions": [],
        "falsified_preconditions": [],
        "falsified_postconditions": []
    },
    {
        "func": "unpause()",
        "type": "PptType.EXIT",
        "executionType": "TxType.NORMAL",
        "preconditions": [],
        "postconditions": [],
        "falsified_preconditions": [],
        "falsified_postconditions": []
    },
    {
        "func": "unpause()",
        "type": "PptType.EXIT",
        "executionType": "TxType.REVERSION",
        "preconditions": [],
        "postconditions": [],
        "falsified_preconditions": [],
        "falsified_postconditions": []
    },
    {
        "func": "claimOwnership()",
        "type": "PptType.EXIT",
        "executionType": "TxType.NORMAL",
        "preconditions": [],
        "postconditions": [],
        "falsified_preconditions": [],
        "falsified_postconditions": []
    },
    {
        "func": "claimOwnership()",
        "type": "PptType.EXIT",
        "executionType": "TxType.REVERSION",
        "preconditions": [],
        "postconditions": [],
        "falsified_preconditions": [],
        "falsified_postconditions": []
    },
    {
        "func": "renounceOwnership()",
        "type": "PptType.EXIT",
        "executionType": "TxType.NORMAL",
        "preconditions": [],
        "postconditions": [],
        "falsified_preconditions": [],
        "falsified_postconditions": []
    },
    {
        "func": "renounceOwnership()",
        "type": "PptType.EXIT",
        "executionType": "TxType.REVERSION",
        "preconditions": [],
        "postconditions": [],
        "falsified_preconditions": [],
        "falsified_postconditions": []
    },
    {
        "func": "pause()",
        "type": "PptType.EXIT",
        "executionType": "TxType.NORMAL",
        "preconditions": [],
        "postconditions": [],
        "falsified_preconditions": [],
        "falsified_postconditions": []
    },
    {
        "func": "pause()",
        "type": "PptType.EXIT",
        "executionType": "TxType.REVERSION",
        "preconditions": [],
        "postconditions": [],
        "falsified_preconditions": [],
        "falsified_postconditions": []
    },
    {
        "func": "burn(account,amount)",
        "type": "PptType.EXIT",
        "executionType": "TxType.NORMAL",
        "preconditions": [],
        "postconditions": [],
        "falsified_preconditions": [],
        "falsified_postconditions": []
    },
    {
        "func": "burn(account,amount)",
        "type": "PptType.EXIT",
        "executionType": "TxType.REVERSION",
        "preconditions": [],
        "postconditions": [],
        "falsified_preconditions": [],
        "falsified_postconditions": []
    },
    {
        "func": "decreaseAllowance(spender,subtractedValue)",
        "type": "PptType.EXIT",
        "executionType": "TxType.NORMAL",
        "preconditions": [],
        "postconditions": [],
        "falsified_preconditions": [],
        "falsified_postconditions": []
    },
    {
        "func": "decreaseAllowance(spender,subtractedValue)",
        "type": "PptType.EXIT",
        "executionType": "TxType.REVERSION",
        "preconditions": [],
        "postconditions": [],
        "falsified_preconditions": [],
        "falsified_postconditions": []
    },
    {
        "func": "transfer(recipient,amount)",
        "type": "PptType.EXIT",
        "executionType": "TxType.NORMAL",
        "preconditions": [
            "VeriSol.Requires(msg.sender != address(0))",
            "VeriSol.Requires(VeriSol.Old(_balances[msg.sender]) > 0)",
            "VeriSol.Requires(VeriSol.Old(uint256(_decimals)) > 0)",
            "VeriSol.Requires(VeriSol.Old(uint256(_decimals)) == 18)",
            "VeriSol.Requires(VeriSol.Old(_owner) != address(0))",
            "VeriSol.Requires(VeriSol.Old(VeriSol.SumMapping(_locked_balances)) == 0)",
            "VeriSol.Requires(VeriSol.Old(paused) == false)",
            "VeriSol.Requires(recipient != address(0))",
            "VeriSol.Requires(amount > 0)",
            "VeriSol.Requires(msg.value == 0)",
            "VeriSol.Requires(VeriSol.Old(_totalSupply) > 0)",
            "VeriSol.Requires(VeriSol.Old(_totalSupply) == 3000000000000000000000000000)",
            "VeriSol.Requires(VeriSol.Old(_pendingowner) == address(0))",
            "VeriSol.Requires(VeriSol.Old(VeriSol.SumMapping(_balances)) > 0)",
            "VeriSol.Requires(VeriSol.Old(VeriSol.SumMapping(_balances)) == 3000000000000000000000000000)",
            "VeriSol.Requires(msg.sender != VeriSol.Old(_pendingowner))",
            "VeriSol.Requires(VeriSol.Old(_balances[msg.sender]) >= VeriSol.Old(uint256(_decimals)))",
            "VeriSol.Requires(VeriSol.Old(_balances[msg.sender]) > VeriSol.Old(uint256(_decimals)))",
            "VeriSol.Requires(VeriSol.Old(_balances[msg.sender]) != VeriSol.Old(uint256(_decimals)))",
            "VeriSol.Requires(VeriSol.Old(_balances[msg.sender]) >= VeriSol.Old(VeriSol.SumMapping(_locked_balances)))",
            "VeriSol.Requires(VeriSol.Old(_balances[msg.sender]) > VeriSol.Old(VeriSol.SumMapping(_locked_balances)))",
            "VeriSol.Requires(VeriSol.Old(_balances[msg.sender]) != VeriSol.Old(VeriSol.SumMapping(_locked_balances)))",
            "VeriSol.Requires(VeriSol.Old(_balances[msg.sender]) >= amount)",
            "VeriSol.Requires(VeriSol.Old(_balances[msg.sender]) >= msg.value)",
            "VeriSol.Requires(VeriSol.Old(_balances[msg.sender]) > msg.value)",
            "VeriSol.Requires(VeriSol.Old(_balances[msg.sender]) != msg.value)",
            "VeriSol.Requires(VeriSol.Old(_balances[msg.sender]) <= VeriSol.Old(_totalSupply))",
            "VeriSol.Requires(VeriSol.Old(_balances[msg.sender]) <= VeriSol.Old(VeriSol.SumMapping(_balances)))",
            "VeriSol.Requires(VeriSol.Old(_balances[recipient]) != VeriSol.Old(uint256(_decimals)))",
            "VeriSol.Requires(VeriSol.Old(_balances[recipient]) >= VeriSol.Old(VeriSol.SumMapping(_locked_balances)))",
            "VeriSol.Requires(VeriSol.Old(_balances[recipient]) >= msg.value)",
            "VeriSol.Requires(VeriSol.Old(_balances[recipient]) <= VeriSol.Old(_totalSupply))",
            "VeriSol.Requires(VeriSol.Old(_balances[recipient]) < VeriSol.Old(_totalSupply))",
            "VeriSol.Requires(VeriSol.Old(_balances[recipient]) != VeriSol.Old(_totalSupply))",
            "VeriSol.Requires(VeriSol.Old(_balances[recipient]) <= VeriSol.Old(VeriSol.SumMapping(_balances)))",
            "VeriSol.Requires(VeriSol.Old(_balances[recipient]) < VeriSol.Old(VeriSol.SumMapping(_balances)))",
            "VeriSol.Requires(VeriSol.Old(_balances[recipient]) != VeriSol.Old(VeriSol.SumMapping(_balances)))",
            "VeriSol.Requires(VeriSol.Old(uint256(_decimals)) >= VeriSol.Old(VeriSol.SumMapping(_locked_balances)))",
            "VeriSol.Requires(VeriSol.Old(uint256(_decimals)) > VeriSol.Old(VeriSol.SumMapping(_locked_balances)))",
            "VeriSol.Requires(VeriSol.Old(uint256(_decimals)) != VeriSol.Old(VeriSol.SumMapping(_locked_balances)))",
            "VeriSol.Requires(VeriSol.Old(uint256(_decimals)) <= amount)",
            "VeriSol.Requires(VeriSol.Old(uint256(_decimals)) < amount)",
            "VeriSol.Requires(VeriSol.Old(uint256(_decimals)) != amount)",
            "VeriSol.Requires(VeriSol.Old(uint256(_decimals)) >= msg.value)",
            "VeriSol.Requires(VeriSol.Old(uint256(_decimals)) > msg.value)",
            "VeriSol.Requires(VeriSol.Old(uint256(_decimals)) != msg.value)",
            "VeriSol.Requires(VeriSol.Old(uint256(_decimals)) <= VeriSol.Old(_totalSupply))",
            "VeriSol.Requires(VeriSol.Old(uint256(_decimals)) < VeriSol.Old(_totalSupply))",
            "VeriSol.Requires(VeriSol.Old(uint256(_decimals)) != VeriSol.Old(_totalSupply))",
            "VeriSol.Requires(VeriSol.Old(uint256(_decimals)) <= VeriSol.Old(VeriSol.SumMapping(_balances)))",
            "VeriSol.Requires(VeriSol.Old(uint256(_decimals)) < VeriSol.Old(VeriSol.SumMapping(_balances)))",
            "VeriSol.Requires(VeriSol.Old(uint256(_decimals)) != VeriSol.Old(VeriSol.SumMapping(_balances)))",
            "VeriSol.Requires(VeriSol.Old(_owner) != recipient)",
            "VeriSol.Requires(VeriSol.Old(_owner) != VeriSol.Old(_pendingowner))",
            "VeriSol.Requires(VeriSol.Old(VeriSol.SumMapping(_locked_balances)) <= amount)",
            "VeriSol.Requires(VeriSol.Old(VeriSol.SumMapping(_locked_balances)) < amount)",
            "VeriSol.Requires(VeriSol.Old(VeriSol.SumMapping(_locked_balances)) != amount)",
            "VeriSol.Requires(VeriSol.Old(VeriSol.SumMapping(_locked_balances)) == msg.value)",
            "VeriSol.Requires(VeriSol.Old(VeriSol.SumMapping(_locked_balances)) >= msg.value)",
            "VeriSol.Requires(VeriSol.Old(VeriSol.SumMapping(_locked_balances)) <= msg.value)",
            "VeriSol.Requires(VeriSol.Old(VeriSol.SumMapping(_locked_balances)) <= VeriSol.Old(_totalSupply))",
            "VeriSol.Requires(VeriSol.Old(VeriSol.SumMapping(_locked_balances)) < VeriSol.Old(_totalSupply))",
            "VeriSol.Requires(VeriSol.Old(VeriSol.SumMapping(_locked_balances)) != VeriSol.Old(_totalSupply))",
            "VeriSol.Requires(VeriSol.Old(VeriSol.SumMapping(_locked_balances)) <= VeriSol.Old(VeriSol.SumMapping(_balances)))",
            "VeriSol.Requires(VeriSol.Old(VeriSol.SumMapping(_locked_balances)) < VeriSol.Old(VeriSol.SumMapping(_balances)))",
            "VeriSol.Requires(VeriSol.Old(VeriSol.SumMapping(_locked_balances)) != VeriSol.Old(VeriSol.SumMapping(_balances)))",
            "VeriSol.Requires(recipient != VeriSol.Old(_pendingowner))",
            "VeriSol.Requires(amount >= msg.value)",
            "VeriSol.Requires(amount > msg.value)",
            "VeriSol.Requires(amount != msg.value)",
            "VeriSol.Requires(amount <= VeriSol.Old(_totalSupply))",
            "VeriSol.Requires(amount <= VeriSol.Old(VeriSol.SumMapping(_balances)))",
            "VeriSol.Requires(msg.value <= VeriSol.Old(_totalSupply))",
            "VeriSol.Requires(msg.value < VeriSol.Old(_totalSupply))",
            "VeriSol.Requires(msg.value != VeriSol.Old(_totalSupply))",
            "VeriSol.Requires(msg.value <= VeriSol.Old(VeriSol.SumMapping(_balances)))",
            "VeriSol.Requires(msg.value < VeriSol.Old(VeriSol.SumMapping(_balances)))",
            "VeriSol.Requires(msg.value != VeriSol.Old(VeriSol.SumMapping(_balances)))",
            "VeriSol.Requires(VeriSol.Old(_totalSupply) == VeriSol.Old(VeriSol.SumMapping(_balances)))",
            "VeriSol.Requires(VeriSol.Old(_totalSupply) >= VeriSol.Old(VeriSol.SumMapping(_balances)))",
            "VeriSol.Requires(VeriSol.Old(_totalSupply) <= VeriSol.Old(VeriSol.SumMapping(_balances)))"
        ],
        "postconditions": [
            "VeriSol.Ensures(_owner != address(0))",
            "VeriSol.Ensures(VeriSol.SumMapping(_balances) > 0)",
            "VeriSol.Ensures(VeriSol.SumMapping(_balances) == 3000000000000000000000000000)",
            "VeriSol.Ensures(paused == false)",
            "VeriSol.Ensures(_balances[recipient] > 0)",
            "VeriSol.Ensures(VeriSol.SumMapping(_locked_balances) == 0)",
            "VeriSol.Ensures(_decimals > 0)",
            "VeriSol.Ensures(_decimals == 18)",
            "VeriSol.Ensures(_pendingowner == address(0))",
            "VeriSol.Ensures(_totalSupply > 0)",
            "VeriSol.Ensures(_totalSupply == 3000000000000000000000000000)",
            "VeriSol.Ensures(_owner == VeriSol.Old(_owner))",
            "VeriSol.Ensures(_owner != recipient)",
            "VeriSol.Ensures(_owner != _pendingowner)",
            "VeriSol.Ensures(_owner != VeriSol.Old(_pendingowner))",
            "VeriSol.Ensures(msg.sender != _pendingowner)",
            "VeriSol.Ensures(_balances[msg.sender] <= VeriSol.Old(_balances[msg.sender]))",
            "VeriSol.Ensures(_balances[msg.sender] <= VeriSol.SumMapping(_balances))",
            "VeriSol.Ensures(_balances[msg.sender] < VeriSol.SumMapping(_balances))",
            "VeriSol.Ensures(_balances[msg.sender] != VeriSol.SumMapping(_balances))",
            "VeriSol.Ensures(_balances[msg.sender] != VeriSol.Old(uint256(_decimals)))",
            "VeriSol.Ensures(_balances[msg.sender] >= VeriSol.Old(VeriSol.SumMapping(_locked_balances)))",
            "VeriSol.Ensures(_balances[msg.sender] >= VeriSol.SumMapping(_locked_balances))",
            "VeriSol.Ensures(_balances[msg.sender] != _decimals)",
            "VeriSol.Ensures(_balances[msg.sender] >= msg.value)",
            "VeriSol.Ensures(_balances[msg.sender] <= VeriSol.Old(_totalSupply))",
            "VeriSol.Ensures(_balances[msg.sender] < VeriSol.Old(_totalSupply))",
            "VeriSol.Ensures(_balances[msg.sender] != VeriSol.Old(_totalSupply))",
            "VeriSol.Ensures(_balances[msg.sender] <= VeriSol.Old(VeriSol.SumMapping(_balances)))",
            "VeriSol.Ensures(_balances[msg.sender] < VeriSol.Old(VeriSol.SumMapping(_balances)))",
            "VeriSol.Ensures(_balances[msg.sender] != VeriSol.Old(VeriSol.SumMapping(_balances)))",
            "VeriSol.Ensures(_balances[msg.sender] <= _totalSupply)",
            "VeriSol.Ensures(_balances[msg.sender] < _totalSupply)",
            "VeriSol.Ensures(_balances[msg.sender] != _totalSupply)",
            "VeriSol.Ensures(VeriSol.Old(_balances[msg.sender]) <= VeriSol.SumMapping(_balances))",
            "VeriSol.Ensures(VeriSol.Old(_balances[msg.sender]) >= VeriSol.SumMapping(_locked_balances))",
            "VeriSol.Ensures(VeriSol.Old(_balances[msg.sender]) > VeriSol.SumMapping(_locked_balances))",
            "VeriSol.Ensures(VeriSol.Old(_balances[msg.sender]) != VeriSol.SumMapping(_locked_balances))",
            "VeriSol.Ensures(VeriSol.Old(_balances[msg.sender]) >= _decimals)",
            "VeriSol.Ensures(VeriSol.Old(_balances[msg.sender]) > _decimals)",
            "VeriSol.Ensures(VeriSol.Old(_balances[msg.sender]) != _decimals)",
            "VeriSol.Ensures(VeriSol.Old(_balances[msg.sender]) <= _totalSupply)",
            "VeriSol.Ensures(VeriSol.Old(_balances[recipient]) <= VeriSol.SumMapping(_balances))",
            "VeriSol.Ensures(VeriSol.Old(_balances[recipient]) < VeriSol.SumMapping(_balances))",
            "VeriSol.Ensures(VeriSol.Old(_balances[recipient]) != VeriSol.SumMapping(_balances))",
            "VeriSol.Ensures(VeriSol.Old(_balances[recipient]) <= _balances[recipient])",
            "VeriSol.Ensures(VeriSol.Old(_balances[recipient]) >= VeriSol.SumMapping(_locked_balances))",
            "VeriSol.Ensures(VeriSol.Old(_balances[recipient]) != _decimals)",
            "VeriSol.Ensures(VeriSol.Old(_balances[recipient]) <= _totalSupply)",
            "VeriSol.Ensures(VeriSol.Old(_balances[recipient]) < _totalSupply)",
            "VeriSol.Ensures(VeriSol.Old(_balances[recipient]) != _totalSupply)",
            "VeriSol.Ensures(VeriSol.SumMapping(_balances) >= VeriSol.Old(uint256(_decimals)))",
            "VeriSol.Ensures(VeriSol.SumMapping(_balances) > VeriSol.Old(uint256(_decimals)))",
            "VeriSol.Ensures(VeriSol.SumMapping(_balances) != VeriSol.Old(uint256(_decimals)))",
            "VeriSol.Ensures(VeriSol.SumMapping(_balances) >= _balances[recipient])",
            "VeriSol.Ensures(VeriSol.SumMapping(_balances) >= VeriSol.Old(VeriSol.SumMapping(_locked_balances)))",
            "VeriSol.Ensures(VeriSol.SumMapping(_balances) > VeriSol.Old(VeriSol.SumMapping(_locked_balances)))",
            "VeriSol.Ensures(VeriSol.SumMapping(_balances) != VeriSol.Old(VeriSol.SumMapping(_locked_balances)))",
            "VeriSol.Ensures(VeriSol.SumMapping(_balances) >= VeriSol.SumMapping(_locked_balances))",
            "VeriSol.Ensures(VeriSol.SumMapping(_balances) > VeriSol.SumMapping(_locked_balances))",
            "VeriSol.Ensures(VeriSol.SumMapping(_balances) != VeriSol.SumMapping(_locked_balances))",
            "VeriSol.Ensures(VeriSol.SumMapping(_balances) >= amount)",
            "VeriSol.Ensures(VeriSol.SumMapping(_balances) >= _decimals)",
            "VeriSol.Ensures(VeriSol.SumMapping(_balances) > _decimals)",
            "VeriSol.Ensures(VeriSol.SumMapping(_balances) != _decimals)",
            "VeriSol.Ensures(VeriSol.SumMapping(_balances) >= msg.value)",
            "VeriSol.Ensures(VeriSol.SumMapping(_balances) > msg.value)",
            "VeriSol.Ensures(VeriSol.SumMapping(_balances) != msg.value)",
            "VeriSol.Ensures(VeriSol.SumMapping(_balances) == VeriSol.Old(_totalSupply))",
            "VeriSol.Ensures(VeriSol.SumMapping(_balances) >= VeriSol.Old(_totalSupply))",
            "VeriSol.Ensures(VeriSol.SumMapping(_balances) <= VeriSol.Old(_totalSupply))",
            "VeriSol.Ensures(VeriSol.SumMapping(_balances) == VeriSol.Old(VeriSol.SumMapping(_balances)))",
            "VeriSol.Ensures(VeriSol.SumMapping(_balances) >= VeriSol.Old(VeriSol.SumMapping(_balances)))",
            "VeriSol.Ensures(VeriSol.SumMapping(_balances) <= VeriSol.Old(VeriSol.SumMapping(_balances)))",
            "VeriSol.Ensures(VeriSol.SumMapping(_balances) == _totalSupply)",
            "VeriSol.Ensures(VeriSol.SumMapping(_balances) >= _totalSupply)",
            "VeriSol.Ensures(VeriSol.SumMapping(_balances) <= _totalSupply)",
            "VeriSol.Ensures(VeriSol.Old(uint256(_decimals)) <= _balances[recipient])",
            "VeriSol.Ensures(VeriSol.Old(uint256(_decimals)) < _balances[recipient])",
            "VeriSol.Ensures(VeriSol.Old(uint256(_decimals)) != _balances[recipient])",
            "VeriSol.Ensures(VeriSol.Old(uint256(_decimals)) >= VeriSol.SumMapping(_locked_balances))",
            "VeriSol.Ensures(VeriSol.Old(uint256(_decimals)) > VeriSol.SumMapping(_locked_balances))",
            "VeriSol.Ensures(VeriSol.Old(uint256(_decimals)) != VeriSol.SumMapping(_locked_balances))",
            "VeriSol.Ensures(VeriSol.Old(uint256(_decimals)) == _decimals)",
            "VeriSol.Ensures(VeriSol.Old(uint256(_decimals)) >= _decimals)",
            "VeriSol.Ensures(VeriSol.Old(uint256(_decimals)) <= _decimals)",
            "VeriSol.Ensures(VeriSol.Old(uint256(_decimals)) <= _totalSupply)",
            "VeriSol.Ensures(VeriSol.Old(uint256(_decimals)) < _totalSupply)",
            "VeriSol.Ensures(VeriSol.Old(uint256(_decimals)) != _totalSupply)",
            "VeriSol.Ensures(VeriSol.Old(_owner) != _pendingowner)",
            "VeriSol.Ensures(_balances[recipient] >= VeriSol.Old(VeriSol.SumMapping(_locked_balances)))",
            "VeriSol.Ensures(_balances[recipient] > VeriSol.Old(VeriSol.SumMapping(_locked_balances)))",
            "VeriSol.Ensures(_balances[recipient] != VeriSol.Old(VeriSol.SumMapping(_locked_balances)))",
            "VeriSol.Ensures(_balances[recipient] >= VeriSol.SumMapping(_locked_balances))",
            "VeriSol.Ensures(_balances[recipient] > VeriSol.SumMapping(_locked_balances))",
            "VeriSol.Ensures(_balances[recipient] != VeriSol.SumMapping(_locked_balances))",
            "VeriSol.Ensures(_balances[recipient] >= amount)",
            "VeriSol.Ensures(_balances[recipient] >= _decimals)",
            "VeriSol.Ensures(_balances[recipient] > _decimals)",
            "VeriSol.Ensures(_balances[recipient] != _decimals)",
            "VeriSol.Ensures(_balances[recipient] >= msg.value)",
            "VeriSol.Ensures(_balances[recipient] > msg.value)",
            "VeriSol.Ensures(_balances[recipient] != msg.value)",
            "VeriSol.Ensures(_balances[recipient] <= VeriSol.Old(_totalSupply))",
            "VeriSol.Ensures(_balances[recipient] <= VeriSol.Old(VeriSol.SumMapping(_balances)))",
            "VeriSol.Ensures(_balances[recipient] <= _totalSupply)",
            "VeriSol.Ensures(VeriSol.Old(VeriSol.SumMapping(_locked_balances)) == VeriSol.SumMapping(_locked_balances))",
            "VeriSol.Ensures(VeriSol.Old(VeriSol.SumMapping(_locked_balances)) >= VeriSol.SumMapping(_locked_balances))",
            "VeriSol.Ensures(VeriSol.Old(VeriSol.SumMapping(_locked_balances)) <= VeriSol.SumMapping(_locked_balances))",
            "VeriSol.Ensures(VeriSol.Old(VeriSol.SumMapping(_locked_balances)) <= _decimals)",
            "VeriSol.Ensures(VeriSol.Old(VeriSol.SumMapping(_locked_balances)) < _decimals)",
            "VeriSol.Ensures(VeriSol.Old(VeriSol.SumMapping(_locked_balances)) != _decimals)",
            "VeriSol.Ensures(VeriSol.Old(VeriSol.SumMapping(_locked_balances)) <= _totalSupply)",
            "VeriSol.Ensures(VeriSol.Old(VeriSol.SumMapping(_locked_balances)) < _totalSupply)",
            "VeriSol.Ensures(VeriSol.Old(VeriSol.SumMapping(_locked_balances)) != _totalSupply)",
            "VeriSol.Ensures(VeriSol.SumMapping(_locked_balances) <= amount)",
            "VeriSol.Ensures(VeriSol.SumMapping(_locked_balances) < amount)",
            "VeriSol.Ensures(VeriSol.SumMapping(_locked_balances) != amount)",
            "VeriSol.Ensures(VeriSol.SumMapping(_locked_balances) <= _decimals)",
            "VeriSol.Ensures(VeriSol.SumMapping(_locked_balances) < _decimals)",
            "VeriSol.Ensures(VeriSol.SumMapping(_locked_balances) != _decimals)",
            "VeriSol.Ensures(VeriSol.SumMapping(_locked_balances) == msg.value)",
            "VeriSol.Ensures(VeriSol.SumMapping(_locked_balances) >= msg.value)",
            "VeriSol.Ensures(VeriSol.SumMapping(_locked_balances) <= msg.value)",
            "VeriSol.Ensures(VeriSol.SumMapping(_locked_balances) <= VeriSol.Old(_totalSupply))",
            "VeriSol.Ensures(VeriSol.SumMapping(_locked_balances) < VeriSol.Old(_totalSupply))",
            "VeriSol.Ensures(VeriSol.SumMapping(_locked_balances) != VeriSol.Old(_totalSupply))",
            "VeriSol.Ensures(VeriSol.SumMapping(_locked_balances) <= VeriSol.Old(VeriSol.SumMapping(_balances)))",
            "VeriSol.Ensures(VeriSol.SumMapping(_locked_balances) < VeriSol.Old(VeriSol.SumMapping(_balances)))",
            "VeriSol.Ensures(VeriSol.SumMapping(_locked_balances) != VeriSol.Old(VeriSol.SumMapping(_balances)))",
            "VeriSol.Ensures(VeriSol.SumMapping(_locked_balances) <= _totalSupply)",
            "VeriSol.Ensures(VeriSol.SumMapping(_locked_balances) < _totalSupply)",
            "VeriSol.Ensures(VeriSol.SumMapping(_locked_balances) != _totalSupply)",
            "VeriSol.Ensures(recipient != _pendingowner)",
            "VeriSol.Ensures(amount >= _decimals)",
            "VeriSol.Ensures(amount > _decimals)",
            "VeriSol.Ensures(amount != _decimals)",
            "VeriSol.Ensures(amount <= _totalSupply)",
            "VeriSol.Ensures(_decimals >= msg.value)",
            "VeriSol.Ensures(_decimals > msg.value)",
            "VeriSol.Ensures(_decimals != msg.value)",
            "VeriSol.Ensures(_decimals <= VeriSol.Old(_totalSupply))",
            "VeriSol.Ensures(_decimals < VeriSol.Old(_totalSupply))",
            "VeriSol.Ensures(_decimals != VeriSol.Old(_totalSupply))",
            "VeriSol.Ensures(_decimals <= VeriSol.Old(VeriSol.SumMapping(_balances)))",
            "VeriSol.Ensures(_decimals < VeriSol.Old(VeriSol.SumMapping(_balances)))",
            "VeriSol.Ensures(_decimals != VeriSol.Old(VeriSol.SumMapping(_balances)))",
            "VeriSol.Ensures(_decimals <= _totalSupply)",
            "VeriSol.Ensures(_decimals < _totalSupply)",
            "VeriSol.Ensures(_decimals != _totalSupply)",
            "VeriSol.Ensures(msg.value <= _totalSupply)",
            "VeriSol.Ensures(msg.value < _totalSupply)",
            "VeriSol.Ensures(msg.value != _totalSupply)",
            "VeriSol.Ensures(_pendingowner == VeriSol.Old(_pendingowner))",
            "VeriSol.Ensures(VeriSol.Old(_totalSupply) == _totalSupply)",
            "VeriSol.Ensures(VeriSol.Old(_totalSupply) >= _totalSupply)",
            "VeriSol.Ensures(VeriSol.Old(_totalSupply) <= _totalSupply)",
            "VeriSol.Ensures(VeriSol.Old(VeriSol.SumMapping(_balances)) == _totalSupply)",
            "VeriSol.Ensures(VeriSol.Old(VeriSol.SumMapping(_balances)) >= _totalSupply)",
            "VeriSol.Ensures(VeriSol.Old(VeriSol.SumMapping(_balances)) <= _totalSupply)"
        ],
        "falsified_preconditions": [
            "VeriSol.Requires(VeriSol.Old(_balances[recipient]) == 0)",
            "VeriSol.Requires(VeriSol.Old(_balances[recipient]) > 0)",
            "VeriSol.Requires(msg.sender != VeriSol.Old(_owner))",
            "VeriSol.Requires(msg.sender != recipient)",
            "VeriSol.Requires(VeriSol.Old(_balances[msg.sender]) >= VeriSol.Old(_balances[recipient]))",
            "VeriSol.Requires(VeriSol.Old(_balances[msg.sender]) > VeriSol.Old(_balances[recipient]))",
            "VeriSol.Requires(VeriSol.Old(_balances[msg.sender]) <= VeriSol.Old(_balances[recipient]))",
            "VeriSol.Requires(VeriSol.Old(_balances[msg.sender]) < VeriSol.Old(_balances[recipient]))",
            "VeriSol.Requires(VeriSol.Old(_balances[msg.sender]) != VeriSol.Old(_balances[recipient]))",
            "VeriSol.Requires(VeriSol.Old(_balances[msg.sender]) == amount)",
            "VeriSol.Requires(VeriSol.Old(_balances[msg.sender]) > amount)",
            "VeriSol.Requires(VeriSol.Old(_balances[msg.sender]) <= amount)",
            "VeriSol.Requires(VeriSol.Old(_balances[msg.sender]) != amount)",
            "VeriSol.Requires(VeriSol.Old(_balances[msg.sender]) < VeriSol.Old(_totalSupply))",
            "VeriSol.Requires(VeriSol.Old(_balances[msg.sender]) != VeriSol.Old(_totalSupply))",
            "VeriSol.Requires(VeriSol.Old(_balances[msg.sender]) < VeriSol.Old(VeriSol.SumMapping(_balances)))",
            "VeriSol.Requires(VeriSol.Old(_balances[msg.sender]) != VeriSol.Old(VeriSol.SumMapping(_balances)))",
            "VeriSol.Requires(VeriSol.Old(_balances[recipient]) >= VeriSol.Old(uint256(_decimals)))",
            "VeriSol.Requires(VeriSol.Old(_balances[recipient]) > VeriSol.Old(uint256(_decimals)))",
            "VeriSol.Requires(VeriSol.Old(_balances[recipient]) <= VeriSol.Old(uint256(_decimals)))",
            "VeriSol.Requires(VeriSol.Old(_balances[recipient]) < VeriSol.Old(uint256(_decimals)))",
            "VeriSol.Requires(VeriSol.Old(_balances[recipient]) == VeriSol.Old(VeriSol.SumMapping(_locked_balances)))",
            "VeriSol.Requires(VeriSol.Old(_balances[recipient]) > VeriSol.Old(VeriSol.SumMapping(_locked_balances)))",
            "VeriSol.Requires(VeriSol.Old(_balances[recipient]) <= VeriSol.Old(VeriSol.SumMapping(_locked_balances)))",
            "VeriSol.Requires(VeriSol.Old(_balances[recipient]) != VeriSol.Old(VeriSol.SumMapping(_locked_balances)))",
            "VeriSol.Requires(VeriSol.Old(_balances[recipient]) == amount)",
            "VeriSol.Requires(VeriSol.Old(_balances[recipient]) >= amount)",
            "VeriSol.Requires(VeriSol.Old(_balances[recipient]) > amount)",
            "VeriSol.Requires(VeriSol.Old(_balances[recipient]) <= amount)",
            "VeriSol.Requires(VeriSol.Old(_balances[recipient]) < amount)",
            "VeriSol.Requires(VeriSol.Old(_balances[recipient]) != amount)",
            "VeriSol.Requires(VeriSol.Old(_balances[recipient]) == msg.value)",
            "VeriSol.Requires(VeriSol.Old(_balances[recipient]) > msg.value)",
            "VeriSol.Requires(VeriSol.Old(_balances[recipient]) <= msg.value)",
            "VeriSol.Requires(VeriSol.Old(_balances[recipient]) != msg.value)",
            "VeriSol.Requires(amount < VeriSol.Old(_totalSupply))",
            "VeriSol.Requires(amount != VeriSol.Old(_totalSupply))",
            "VeriSol.Requires(amount < VeriSol.Old(VeriSol.SumMapping(_balances)))",
            "VeriSol.Requires(amount != VeriSol.Old(VeriSol.SumMapping(_balances)))"
        ],
        "falsified_postconditions": [
            "VeriSol.Ensures(_balances[msg.sender] == 0)",
            "VeriSol.Ensures(_balances[msg.sender] > 0)",
            "VeriSol.Ensures(_owner != msg.sender)",
            "VeriSol.Ensures(_balances[msg.sender] < VeriSol.Old(_balances[msg.sender]))",
            "VeriSol.Ensures(_balances[msg.sender] != VeriSol.Old(_balances[msg.sender]))",
            "VeriSol.Ensures(_balances[msg.sender] == VeriSol.Old(_balances[recipient]))",
            "VeriSol.Ensures(_balances[msg.sender] >= VeriSol.Old(_balances[recipient]))",
            "VeriSol.Ensures(_balances[msg.sender] > VeriSol.Old(_balances[recipient]))",
            "VeriSol.Ensures(_balances[msg.sender] <= VeriSol.Old(_balances[recipient]))",
            "VeriSol.Ensures(_balances[msg.sender] < VeriSol.Old(_balances[recipient]))",
            "VeriSol.Ensures(_balances[msg.sender] != VeriSol.Old(_balances[recipient]))",
            "VeriSol.Ensures(_balances[msg.sender] >= VeriSol.Old(uint256(_decimals)))",
            "VeriSol.Ensures(_balances[msg.sender] > VeriSol.Old(uint256(_decimals)))",
            "VeriSol.Ensures(_balances[msg.sender] <= VeriSol.Old(uint256(_decimals)))",
            "VeriSol.Ensures(_balances[msg.sender] < VeriSol.Old(uint256(_decimals)))",
            "VeriSol.Ensures(_balances[msg.sender] >= _balances[recipient])",
            "VeriSol.Ensures(_balances[msg.sender] > _balances[recipient])",
            "VeriSol.Ensures(_balances[msg.sender] <= _balances[recipient])",
            "VeriSol.Ensures(_balances[msg.sender] < _balances[recipient])",
            "VeriSol.Ensures(_balances[msg.sender] != _balances[recipient])",
            "VeriSol.Ensures(_balances[msg.sender] == VeriSol.Old(VeriSol.SumMapping(_locked_balances)))",
            "VeriSol.Ensures(_balances[msg.sender] > VeriSol.Old(VeriSol.SumMapping(_locked_balances)))",
            "VeriSol.Ensures(_balances[msg.sender] <= VeriSol.Old(VeriSol.SumMapping(_locked_balances)))",
            "VeriSol.Ensures(_balances[msg.sender] != VeriSol.Old(VeriSol.SumMapping(_locked_balances)))",
            "VeriSol.Ensures(_balances[msg.sender] == VeriSol.SumMapping(_locked_balances))",
            "VeriSol.Ensures(_balances[msg.sender] > VeriSol.SumMapping(_locked_balances))",
            "VeriSol.Ensures(_balances[msg.sender] <= VeriSol.SumMapping(_locked_balances))",
            "VeriSol.Ensures(_balances[msg.sender] != VeriSol.SumMapping(_locked_balances))",
            "VeriSol.Ensures(_balances[msg.sender] >= amount)",
            "VeriSol.Ensures(_balances[msg.sender] > amount)",
            "VeriSol.Ensures(_balances[msg.sender] <= amount)",
            "VeriSol.Ensures(_balances[msg.sender] < amount)",
            "VeriSol.Ensures(_balances[msg.sender] != amount)",
            "VeriSol.Ensures(_balances[msg.sender] >= _decimals)",
            "VeriSol.Ensures(_balances[msg.sender] > _decimals)",
            "VeriSol.Ensures(_balances[msg.sender] <= _decimals)",
            "VeriSol.Ensures(_balances[msg.sender] < _decimals)",
            "VeriSol.Ensures(_balances[msg.sender] == msg.value)",
            "VeriSol.Ensures(_balances[msg.sender] > msg.value)",
            "VeriSol.Ensures(_balances[msg.sender] <= msg.value)",
            "VeriSol.Ensures(_balances[msg.sender] != msg.value)",
            "VeriSol.Ensures(VeriSol.Old(_balances[msg.sender]) < VeriSol.SumMapping(_balances))",
            "VeriSol.Ensures(VeriSol.Old(_balances[msg.sender]) != VeriSol.SumMapping(_balances))",
            "VeriSol.Ensures(VeriSol.Old(_balances[msg.sender]) == _balances[recipient])",
            "VeriSol.Ensures(VeriSol.Old(_balances[msg.sender]) >= _balances[recipient])",
            "VeriSol.Ensures(VeriSol.Old(_balances[msg.sender]) > _balances[recipient])",
            "VeriSol.Ensures(VeriSol.Old(_balances[msg.sender]) <= _balances[recipient])",
            "VeriSol.Ensures(VeriSol.Old(_balances[msg.sender]) < _balances[recipient])",
            "VeriSol.Ensures(VeriSol.Old(_balances[msg.sender]) != _balances[recipient])",
            "VeriSol.Ensures(VeriSol.Old(_balances[msg.sender]) < _totalSupply)",
            "VeriSol.Ensures(VeriSol.Old(_balances[msg.sender]) != _totalSupply)",
            "VeriSol.Ensures(VeriSol.Old(_balances[recipient]) < _balances[recipient])",
            "VeriSol.Ensures(VeriSol.Old(_balances[recipient]) != _balances[recipient])",
            "VeriSol.Ensures(VeriSol.Old(_balances[recipient]) == VeriSol.SumMapping(_locked_balances))",
            "VeriSol.Ensures(VeriSol.Old(_balances[recipient]) > VeriSol.SumMapping(_locked_balances))",
            "VeriSol.Ensures(VeriSol.Old(_balances[recipient]) <= VeriSol.SumMapping(_locked_balances))",
            "VeriSol.Ensures(VeriSol.Old(_balances[recipient]) != VeriSol.SumMapping(_locked_balances))",
            "VeriSol.Ensures(VeriSol.Old(_balances[recipient]) >= _decimals)",
            "VeriSol.Ensures(VeriSol.Old(_balances[recipient]) > _decimals)",
            "VeriSol.Ensures(VeriSol.Old(_balances[recipient]) <= _decimals)",
            "VeriSol.Ensures(VeriSol.Old(_balances[recipient]) < _decimals)",
            "VeriSol.Ensures(VeriSol.SumMapping(_balances) > _balances[recipient])",
            "VeriSol.Ensures(VeriSol.SumMapping(_balances) != _balances[recipient])",
            "VeriSol.Ensures(VeriSol.SumMapping(_balances) > amount)",
            "VeriSol.Ensures(VeriSol.SumMapping(_balances) != amount)",
            "VeriSol.Ensures(_balances[recipient] == amount)",
            "VeriSol.Ensures(_balances[recipient] > amount)",
            "VeriSol.Ensures(_balances[recipient] <= amount)",
            "VeriSol.Ensures(_balances[recipient] != amount)",
            "VeriSol.Ensures(_balances[recipient] < VeriSol.Old(_totalSupply))",
            "VeriSol.Ensures(_balances[recipient] != VeriSol.Old(_totalSupply))",
            "VeriSol.Ensures(_balances[recipient] < VeriSol.Old(VeriSol.SumMapping(_balances)))",
            "VeriSol.Ensures(_balances[recipient] != VeriSol.Old(VeriSol.SumMapping(_balances)))",
            "VeriSol.Ensures(_balances[recipient] < _totalSupply)",
            "VeriSol.Ensures(_balances[recipient] != _totalSupply)",
            "VeriSol.Ensures(amount < _totalSupply)",
            "VeriSol.Ensures(amount != _totalSupply)",
            "VeriSol.Ensures(amount + _balances[msg.sender] == VeriSol.Old(_balances[msg.sender]))",
            "VeriSol.Ensures(VeriSol.Old(_totalSupply) - amount == _balances[msg.sender])",
            "VeriSol.Ensures(VeriSol.Old(VeriSol.SumMapping(_balances)) - amount == _balances[msg.sender])"
        ]
    },
    {
        "func": "transfer(recipient,amount)",
        "type": "PptType.EXIT",
        "executionType": "TxType.REVERSION",
        "preconditions": [],
        "postconditions": [],
        "falsified_preconditions": [],
        "falsified_postconditions": []
    },
    {
        "func": "collectFromLocked(addresses,amounts,recipient)",
        "type": "PptType.EXIT",
        "executionType": "TxType.NORMAL",
        "preconditions": [],
        "postconditions": [],
        "falsified_preconditions": [],
        "falsified_postconditions": []
    },
    {
        "func": "collectFromLocked(addresses,amounts,recipient)",
        "type": "PptType.EXIT",
        "executionType": "TxType.REVERSION",
        "preconditions": [],
        "postconditions": [],
        "falsified_preconditions": [],
        "falsified_postconditions": []
    },
    {
        "func": "lockTokenWhole(addresses)",
        "type": "PptType.EXIT",
        "executionType": "TxType.NORMAL",
        "preconditions": [],
        "postconditions": [],
        "falsified_preconditions": [],
        "falsified_postconditions": []
    },
    {
        "func": "lockTokenWhole(addresses)",
        "type": "PptType.EXIT",
        "executionType": "TxType.REVERSION",
        "preconditions": [],
        "postconditions": [],
        "falsified_preconditions": [],
        "falsified_postconditions": []
    },
    {
        "func": "unlockToken(addresses,amounts)",
        "type": "PptType.EXIT",
        "executionType": "TxType.NORMAL",
        "preconditions": [],
        "postconditions": [],
        "falsified_preconditions": [],
        "falsified_postconditions": []
    },
    {
        "func": "unlockToken(addresses,amounts)",
        "type": "PptType.EXIT",
        "executionType": "TxType.REVERSION",
        "preconditions": [],
        "postconditions": [],
        "falsified_preconditions": [],
        "falsified_postconditions": []
    },
    {
        "func": "transferOwnership(newOwner)",
        "type": "PptType.EXIT",
        "executionType": "TxType.NORMAL",
        "preconditions": [],
        "postconditions": [],
        "falsified_preconditions": [],
        "falsified_postconditions": []
    },
    {
        "func": "transferOwnership(newOwner)",
        "type": "PptType.EXIT",
        "executionType": "TxType.REVERSION",
        "preconditions": [],
        "postconditions": [],
        "falsified_preconditions": [],
        "falsified_postconditions": []
    },
    {
        "func": "lockToken(addresses,amounts)",
        "type": "PptType.EXIT",
        "executionType": "TxType.NORMAL",
        "preconditions": [],
        "postconditions": [],
        "falsified_preconditions": [],
        "falsified_postconditions": []
    },
    {
        "func": "lockToken(addresses,amounts)",
        "type": "PptType.EXIT",
        "executionType": "TxType.REVERSION",
        "preconditions": [],
        "postconditions": [],
        "falsified_preconditions": [],
        "falsified_postconditions": []
    },
    {
        "func": null,
        "type": "PptType.CONTRACT",
        "executionType": "TxType.NORMAL",
        "preconditions": [
            "VeriSol.Requires(VeriSol.Old(uint256(_decimals)) > 0)",
            "VeriSol.Requires(VeriSol.Old(uint256(_decimals)) == 18)",
            "VeriSol.Requires(VeriSol.Old(_owner) != address(0))",
            "VeriSol.Requires(VeriSol.Old(VeriSol.SumMapping(_locked_balances)) == 0)",
            "VeriSol.Requires(VeriSol.Old(paused) == false)",
            "VeriSol.Requires(VeriSol.Old(_totalSupply) > 0)",
            "VeriSol.Requires(VeriSol.Old(_totalSupply) == 3000000000000000000000000000)",
            "VeriSol.Requires(VeriSol.Old(_pendingowner) == address(0))",
            "VeriSol.Requires(VeriSol.Old(VeriSol.SumMapping(_balances)) > 0)",
            "VeriSol.Requires(VeriSol.Old(VeriSol.SumMapping(_balances)) == 3000000000000000000000000000)",
            "VeriSol.Requires(VeriSol.Old(uint256(_decimals)) >= VeriSol.Old(VeriSol.SumMapping(_locked_balances)))",
            "VeriSol.Requires(VeriSol.Old(uint256(_decimals)) > VeriSol.Old(VeriSol.SumMapping(_locked_balances)))",
            "VeriSol.Requires(VeriSol.Old(uint256(_decimals)) != VeriSol.Old(VeriSol.SumMapping(_locked_balances)))",
            "VeriSol.Requires(VeriSol.Old(uint256(_decimals)) <= VeriSol.Old(_totalSupply))",
            "VeriSol.Requires(VeriSol.Old(uint256(_decimals)) < VeriSol.Old(_totalSupply))",
            "VeriSol.Requires(VeriSol.Old(uint256(_decimals)) != VeriSol.Old(_totalSupply))",
            "VeriSol.Requires(VeriSol.Old(uint256(_decimals)) <= VeriSol.Old(VeriSol.SumMapping(_balances)))",
            "VeriSol.Requires(VeriSol.Old(uint256(_decimals)) < VeriSol.Old(VeriSol.SumMapping(_balances)))",
            "VeriSol.Requires(VeriSol.Old(uint256(_decimals)) != VeriSol.Old(VeriSol.SumMapping(_balances)))",
            "VeriSol.Requires(VeriSol.Old(_owner) != VeriSol.Old(_pendingowner))",
            "VeriSol.Requires(VeriSol.Old(VeriSol.SumMapping(_locked_balances)) <= VeriSol.Old(_totalSupply))",
            "VeriSol.Requires(VeriSol.Old(VeriSol.SumMapping(_locked_balances)) < VeriSol.Old(_totalSupply))",
            "VeriSol.Requires(VeriSol.Old(VeriSol.SumMapping(_locked_balances)) != VeriSol.Old(_totalSupply))",
            "VeriSol.Requires(VeriSol.Old(VeriSol.SumMapping(_locked_balances)) <= VeriSol.Old(VeriSol.SumMapping(_balances)))",
            "VeriSol.Requires(VeriSol.Old(VeriSol.SumMapping(_locked_balances)) < VeriSol.Old(VeriSol.SumMapping(_balances)))",
            "VeriSol.Requires(VeriSol.Old(VeriSol.SumMapping(_locked_balances)) != VeriSol.Old(VeriSol.SumMapping(_balances)))",
            "VeriSol.Requires(VeriSol.Old(_totalSupply) == VeriSol.Old(VeriSol.SumMapping(_balances)))",
            "VeriSol.Requires(VeriSol.Old(_totalSupply) >= VeriSol.Old(VeriSol.SumMapping(_balances)))",
            "VeriSol.Requires(VeriSol.Old(_totalSupply) <= VeriSol.Old(VeriSol.SumMapping(_balances)))"
        ],
        "postconditions": [
            "VeriSol.Ensures(_owner != address(0))",
            "VeriSol.Ensures(VeriSol.SumMapping(_balances) > 0)",
            "VeriSol.Ensures(VeriSol.SumMapping(_balances) == 3000000000000000000000000000)",
            "VeriSol.Ensures(paused == false)",
            "VeriSol.Ensures(VeriSol.SumMapping(_locked_balances) == 0)",
            "VeriSol.Ensures(_decimals > 0)",
            "VeriSol.Ensures(_decimals == 18)",
            "VeriSol.Ensures(_pendingowner == address(0))",
            "VeriSol.Ensures(_totalSupply > 0)",
            "VeriSol.Ensures(_totalSupply == 3000000000000000000000000000)",
            "VeriSol.Ensures(_owner == VeriSol.Old(_owner))",
            "VeriSol.Ensures(_owner != _pendingowner)",
            "VeriSol.Ensures(_owner != VeriSol.Old(_pendingowner))",
            "VeriSol.Ensures(VeriSol.SumMapping(_balances) >= VeriSol.Old(uint256(_decimals)))",
            "VeriSol.Ensures(VeriSol.SumMapping(_balances) > VeriSol.Old(uint256(_decimals)))",
            "VeriSol.Ensures(VeriSol.SumMapping(_balances) != VeriSol.Old(uint256(_decimals)))",
            "VeriSol.Ensures(VeriSol.SumMapping(_balances) >= VeriSol.Old(VeriSol.SumMapping(_locked_balances)))",
            "VeriSol.Ensures(VeriSol.SumMapping(_balances) > VeriSol.Old(VeriSol.SumMapping(_locked_balances)))",
            "VeriSol.Ensures(VeriSol.SumMapping(_balances) != VeriSol.Old(VeriSol.SumMapping(_locked_balances)))",
            "VeriSol.Ensures(VeriSol.SumMapping(_balances) >= VeriSol.SumMapping(_locked_balances))",
            "VeriSol.Ensures(VeriSol.SumMapping(_balances) > VeriSol.SumMapping(_locked_balances))",
            "VeriSol.Ensures(VeriSol.SumMapping(_balances) != VeriSol.SumMapping(_locked_balances))",
            "VeriSol.Ensures(VeriSol.SumMapping(_balances) >= _decimals)",
            "VeriSol.Ensures(VeriSol.SumMapping(_balances) > _decimals)",
            "VeriSol.Ensures(VeriSol.SumMapping(_balances) != _decimals)",
            "VeriSol.Ensures(VeriSol.SumMapping(_balances) == VeriSol.Old(_totalSupply))",
            "VeriSol.Ensures(VeriSol.SumMapping(_balances) >= VeriSol.Old(_totalSupply))",
            "VeriSol.Ensures(VeriSol.SumMapping(_balances) <= VeriSol.Old(_totalSupply))",
            "VeriSol.Ensures(VeriSol.SumMapping(_balances) == VeriSol.Old(VeriSol.SumMapping(_balances)))",
            "VeriSol.Ensures(VeriSol.SumMapping(_balances) >= VeriSol.Old(VeriSol.SumMapping(_balances)))",
            "VeriSol.Ensures(VeriSol.SumMapping(_balances) <= VeriSol.Old(VeriSol.SumMapping(_balances)))",
            "VeriSol.Ensures(VeriSol.SumMapping(_balances) == _totalSupply)",
            "VeriSol.Ensures(VeriSol.SumMapping(_balances) >= _totalSupply)",
            "VeriSol.Ensures(VeriSol.SumMapping(_balances) <= _totalSupply)",
            "VeriSol.Ensures(VeriSol.Old(uint256(_decimals)) >= VeriSol.SumMapping(_locked_balances))",
            "VeriSol.Ensures(VeriSol.Old(uint256(_decimals)) > VeriSol.SumMapping(_locked_balances))",
            "VeriSol.Ensures(VeriSol.Old(uint256(_decimals)) != VeriSol.SumMapping(_locked_balances))",
            "VeriSol.Ensures(VeriSol.Old(uint256(_decimals)) == _decimals)",
            "VeriSol.Ensures(VeriSol.Old(uint256(_decimals)) >= _decimals)",
            "VeriSol.Ensures(VeriSol.Old(uint256(_decimals)) <= _decimals)",
            "VeriSol.Ensures(VeriSol.Old(uint256(_decimals)) <= _totalSupply)",
            "VeriSol.Ensures(VeriSol.Old(uint256(_decimals)) < _totalSupply)",
            "VeriSol.Ensures(VeriSol.Old(uint256(_decimals)) != _totalSupply)",
            "VeriSol.Ensures(VeriSol.Old(_owner) != _pendingowner)",
            "VeriSol.Ensures(VeriSol.Old(VeriSol.SumMapping(_locked_balances)) == VeriSol.SumMapping(_locked_balances))",
            "VeriSol.Ensures(VeriSol.Old(VeriSol.SumMapping(_locked_balances)) >= VeriSol.SumMapping(_locked_balances))",
            "VeriSol.Ensures(VeriSol.Old(VeriSol.SumMapping(_locked_balances)) <= VeriSol.SumMapping(_locked_balances))",
            "VeriSol.Ensures(VeriSol.Old(VeriSol.SumMapping(_locked_balances)) <= _decimals)",
            "VeriSol.Ensures(VeriSol.Old(VeriSol.SumMapping(_locked_balances)) < _decimals)",
            "VeriSol.Ensures(VeriSol.Old(VeriSol.SumMapping(_locked_balances)) != _decimals)",
            "VeriSol.Ensures(VeriSol.Old(VeriSol.SumMapping(_locked_balances)) <= _totalSupply)",
            "VeriSol.Ensures(VeriSol.Old(VeriSol.SumMapping(_locked_balances)) < _totalSupply)",
            "VeriSol.Ensures(VeriSol.Old(VeriSol.SumMapping(_locked_balances)) != _totalSupply)",
            "VeriSol.Ensures(VeriSol.SumMapping(_locked_balances) <= _decimals)",
            "VeriSol.Ensures(VeriSol.SumMapping(_locked_balances) < _decimals)",
            "VeriSol.Ensures(VeriSol.SumMapping(_locked_balances) != _decimals)",
            "VeriSol.Ensures(VeriSol.SumMapping(_locked_balances) <= VeriSol.Old(_totalSupply))",
            "VeriSol.Ensures(VeriSol.SumMapping(_locked_balances) < VeriSol.Old(_totalSupply))",
            "VeriSol.Ensures(VeriSol.SumMapping(_locked_balances) != VeriSol.Old(_totalSupply))",
            "VeriSol.Ensures(VeriSol.SumMapping(_locked_balances) <= VeriSol.Old(VeriSol.SumMapping(_balances)))",
            "VeriSol.Ensures(VeriSol.SumMapping(_locked_balances) < VeriSol.Old(VeriSol.SumMapping(_balances)))",
            "VeriSol.Ensures(VeriSol.SumMapping(_locked_balances) != VeriSol.Old(VeriSol.SumMapping(_balances)))",
            "VeriSol.Ensures(VeriSol.SumMapping(_locked_balances) <= _totalSupply)",
            "VeriSol.Ensures(VeriSol.SumMapping(_locked_balances) < _totalSupply)",
            "VeriSol.Ensures(VeriSol.SumMapping(_locked_balances) != _totalSupply)",
            "VeriSol.Ensures(_decimals <= VeriSol.Old(_totalSupply))",
            "VeriSol.Ensures(_decimals < VeriSol.Old(_totalSupply))",
            "VeriSol.Ensures(_decimals != VeriSol.Old(_totalSupply))",
            "VeriSol.Ensures(_decimals <= VeriSol.Old(VeriSol.SumMapping(_balances)))",
            "VeriSol.Ensures(_decimals < VeriSol.Old(VeriSol.SumMapping(_balances)))",
            "VeriSol.Ensures(_decimals != VeriSol.Old(VeriSol.SumMapping(_balances)))",
            "VeriSol.Ensures(_decimals <= _totalSupply)",
            "VeriSol.Ensures(_decimals < _totalSupply)",
            "VeriSol.Ensures(_decimals != _totalSupply)",
            "VeriSol.Ensures(_pendingowner == VeriSol.Old(_pendingowner))",
            "VeriSol.Ensures(VeriSol.Old(_totalSupply) == _totalSupply)",
            "VeriSol.Ensures(VeriSol.Old(_totalSupply) >= _totalSupply)",
            "VeriSol.Ensures(VeriSol.Old(_totalSupply) <= _totalSupply)",
            "VeriSol.Ensures(VeriSol.Old(VeriSol.SumMapping(_balances)) == _totalSupply)",
            "VeriSol.Ensures(VeriSol.Old(VeriSol.SumMapping(_balances)) >= _totalSupply)",
            "VeriSol.Ensures(VeriSol.Old(VeriSol.SumMapping(_balances)) <= _totalSupply)"
        ],
        "falsified_preconditions": [],
        "falsified_postconditions": []
    }
]